Workbook

Sheet Read me
B2: Resources and prep, Years 7 and 8, Weeks 1 to 10
B3: All weeks: every resource for every Year 7 and Year 8 lesson on one sheet, grouped by kind (printing, card and stationery, equipment, food and consumables, things to make). Filter by week, year or group. Pink cells are the ones to check.
B4: Prep by week: every prep task with when it happens, how long it takes and who could do it, and a week-by-week total so you can see where the load falls.
B5: Cut the prep: the options for reducing the prep, with the minutes each one saves.
B6: Quantities are for one class of up to 24 students in 6 groups. Type the number of classes and the Year 7 freezer plan in the yellow cells at the top of the All weeks sheet. The "Got it" column is for your ticks.
B7: Checked against every lesson file (lesson plan, kit card, printables), the designed printables, the Teacher Guide prep calendar and the Year 8 Case Bible, and compared with the full requisition workbook. Items already made in an earlier week are listed with "Already have" and are not counted again in the printing totals.
B9: Items missing from the full requisition: 6 rows marked "No: add" on the All weeks sheet.

Sheet All weeks
A1: Years 7 and 8, Weeks 1 to 10: resources needed
A2: Every lesson on one sheet. Quantities are for one class of up to 24 students in 6 groups. Change the yellow cells; totals update. Use the filter arrows to show one week, one year or one group.
A3: Year 7 classes | C3: 1 | D3: Items per student, per group or per class are multiplied by the classes in that year. | J3: Printing, all weeks (sheets)
A4: Year 8 classes | C4: 1 | J4: A4 paper | L4: =SUMIFS($L$9:$L$721,$J$9:$J$721,J4) -> 1987 | M4: A4 card | O4: =SUMIFS($L$9:$L$721,$J$9:$J$721,M4) -> 176
A5: Year 7 freezer plan | C5: A and B | D5: A (freezer), B (no freezer) or "A and B". Items for the plan not chosen count as 0. Decide by Week 4. | J5: A3 paper | L5: =SUMIFS($L$9:$L$721,$J$9:$J$721,J5) -> 36 | M5: A4 90 gsm (booklet) | O5: =SUMIFS($L$9:$L$721,$J$9:$J$721,M5) -> 196
J6: A5 paper | L6: =SUMIFS($L$9:$L$721,$J$9:$J$721,J6) -> 160
A8: Week | B8: Year | C8: Group | D8: Item | E8: Quantity (one class) | F8: Unit or how to print | G8: Per | H8: Plan | I8: Total for your classes | J8: Paper or card | K8: Sheets per copy | L8: Sheets in total | M8: What it is for | N8: Optional? | O8: Already have (from an earlier week) | P8: On the requisition? | Q8: Check | R8: Got it
A9: 1 | B9: Year 7 | C9: Printing (paper copies) | D9: Skills Check paper, Year 7 (Week 1 baseline) | E9: 24 | F9: copies; 5 A4 portrait pages, double-sided (3 sheets each, last side blank) | G9: per student | I9: =IF(E9="","",IF(OR(AND(H9="Plan A",$C$5="B"),AND(H9="Plan B",$C$5="A")),0,IF(OR(G9="per student",G9="per group",G9="per class"),E9*IF(B9="Year 7",$C$3,$C$4),E9))) -> 24 | J9: A4 paper | K9: 3 | L9: =IF(OR(K9="",O9<>"",I9=""),"",ROUNDUP(I9*K9,0)) -> 72 | M9: 15-minute baseline skills check done alone in silence; marked out of 20, entered in the tracker and filed in the class assessment folder, not returned until after Week 10. | P9: No: paper printing | Q9: Skills_Check_Y7.md Section 1 says 'two sides of A4', but the designed paper is 5 pages ('Page 1 of 5' to 'Page 5 of 5'), so 3 sheets double-sided (or 5 single-sided). Decide whether to staple (no stapler is named). No spares stated. Print from the master that Week 10 will use again and do not change it in between.
A10: 1 | B10: Year 7 | C10: Printing (paper copies) | D10: Interest survey | E10: 24 | F10: copies; half-A4, 2 per A4 sheet, single-sided, cut in half (12 sheets) | G10: per student | I10: =IF(E10="","",IF(OR(AND(H10="Plan A",$C$5="B"),AND(H10="Plan B",$C$5="A")),0,IF(OR(G10="per student",G10="per group",G10="per class"),E10*IF(B10="Year 7",$C$3,$C$4),E10))) -> 24 | J10: A4 paper | K10: 0.5 | L10: =IF(OR(K10="",O10<>"",I10=""),"",ROUNDUP(I10*K10,0)) -> 12 | M10: 3-minute Week 1 baseline survey straight after the skills check; six scores per student go into the tracker. | P10: No: paper printing | Q10: Fresh copies are needed again in Week 10. No spares stated.
A11: 1 | B11: Year 7 | C11: Printing (paper copies) | D11: Student worksheet, What do scientists do? | E11: 24 | F11: copies; 4 A4 portrait pages, double-sided (2 sheets each) | G11: per student | I11: =IF(E11="","",IF(OR(AND(H11="Plan A",$C$5="B"),AND(H11="Plan B",$C$5="A")),0,IF(OR(G11="per student",G11="per group",G11="per class"),E11*IF(B11="Year 7",$C$3,$C$4),E11))) -> 24 | J11: A4 paper | K11: 2 | L11: =IF(OR(K11="",O11<>"",I11=""),"",ROUNDUP(I11*K11,0)) -> 48 | M11: Core A observation or inference sort, Core B footprint table, Stretch, Challenge, My thinking box, fold-under word bank and the exit ticket strip. | P11: No: paper printing | Q11: The exit ticket strip at the foot of page 4 sits below a cut line; printed double-sided, cutting it off also cuts the foot of page 3 (the My thinking box). Check the layout before printing. Print only from the design rebuilt after the language pass and discard any earlier copies. No spares stated.
A12: 1 | B12: Year 7 | C12: Printing (paper copies) | D12: Skills Check mark scheme (teacher copy) | E12: 1 | F12: teacher copy; 2 A4 pages (single-sided here; sides not stated) | G12: per once | I12: =IF(E12="","",IF(OR(AND(H12="Plan A",$C$5="B"),AND(H12="Plan B",$C$5="A")),0,IF(OR(G12="per student",G12="per group",G12="per class"),E12*IF(B12="Year 7",$C$3,$C$4),E12))) -> 1 | J12: A4 paper | K12: 2 | L12: =IF(OR(K12="",O12<>"",I12=""),"",ROUNDUP(I12*K12,0)) -> 2 | M12: Marking the skills checks out of 20 within Week 1; kept for Week 10. | P12: No: paper printing | Q12: Single- or double-sided is not stated (1 sheet if double-sided). One copy serves every class.
A13: 1 | B13: Year 7 | C13: Printing (paper copies) | D13: Kit card, Y7 Week 1 (teacher copy) | E13: 1 | F13: teacher copy; half-A4 (A5), single-sided, printed on A4 | G13: per once | I13: =IF(E13="","",IF(OR(AND(H13="Plan A",$C$5="B"),AND(H13="Plan B",$C$5="A")),0,IF(OR(G13="per student",G13="per group",G13="per class"),E13*IF(B13="Year 7",$C$3,$C$4),E13))) -> 1 | J13: A4 paper | K13: 1 | L13: =IF(OR(K13="",O13<>"",I13=""),"",ROUNDUP(I13*K13,0)) -> 1 | M13: Kit list per group and per student, teacher prep with times, hazards and clean-up. | P13: No: paper printing | Q13: It still says 'Group role cards: 1 set of 5'; the role card set now has 6 cards.
A14: 1 | B14: Year 7 | C14: Printing (paper copies) | D14: Group role cards with duties (including Language buddy) | E14: 6 | F14: sets; 1 A4 sheet per set (6 business-card size cards, 85 mm by 55 mm, with cut lines), single-sided | G14: per group | I14: =IF(E14="","",IF(OR(AND(H14="Plan A",$C$5="B"),AND(H14="Plan B",$C$5="A")),0,IF(OR(G14="per student",G14="per group",G14="per class"),E14*IF(B14="Year 7",$C$3,$C$4),E14))) -> 6 | J14: A4 paper | K14: 1 | L14: =IF(OR(K14="",O14<>"",I14=""),"",ROUNDUP(I14*K14,0)) -> 6 | M14: One set per table: Lead Scientist, Measurer, Recorder, Safety Officer, Reporter and Language buddy, duties in both languages; laminated, cut and kept all term. | P14: No: paper printing | Q14: The Week 1 kit card says '1 set of 5'; the language support pack, the design and the requisition use 6 cards per set. Paper or card is not stated. Lamination is the A4 pouch row.
A15: 1 | B15: Year 7 | C15: Printing (paper copies) | D15: Classroom language card (two-sided) | E15: 30 | F15: cards; A5 landscape, double-sided (1 per student plus 6 spares) | G15: per student | I15: =IF(E15="","",IF(OR(AND(H15="Plan A",$C$5="B"),AND(H15="Plan B",$C$5="A")),0,IF(OR(G15="per student",G15="per group",G15="per class"),E15*IF(B15="Year 7",$C$3,$C$4),E15))) -> 30 | J15: A5 paper | K15: 1 | L15: =IF(OR(K15="",O15<>"",I15=""),"",ROUNDUP(I15*K15,0)) -> 30 | M15: Side A teacher routine phrases, side B student help phrases; laminated, handed out with a two-minute walk-through and kept all term. | P15: No: paper printing | Q15: Paper to print on is not stated (30 A5 sheets, or 15 A4 sheets cut in half). The Week 1 timeline has no slot for the walk-through. Lamination is the A5 pouch row.
A16: 1 | B16: Year 7 | C16: Printing (paper copies) | D16: Language support A3 posters: Instruction words key, Classroom language (side B), Think in any language | E16: 3 | F16: posters; 1 of each, A3, single-sided | G16: per room | I16: =IF(E16="","",IF(OR(AND(H16="Plan A",$C$5="B"),AND(H16="Plan B",$C$5="A")),0,IF(OR(G16="per student",G16="per group",G16="per class"),E16*IF(B16="Year 7",$C$3,$C$4),E16))) -> 3 | J16: A3 paper | K16: 1 | L16: =IF(OR(K16="",O16<>"",I16=""),"",ROUNDUP(I16*K16,0)) -> 3 | M16: Wall posters kept up all term. | P16: Yes | Q16: No source says to laminate them. Covered by the requisition's 3 sheets of A3 paper.
A17: 1 | B17: Year 7 | C17: Printing (paper copies) | D17: Sentence frame bank poster, Ice Engineers | E17: 1 | F17: poster; A4 portrait, single-sided | G17: per room | I17: =IF(E17="","",IF(OR(AND(H17="Plan A",$C$5="B"),AND(H17="Plan B",$C$5="A")),0,IF(OR(G17="per student",G17="per group",G17="per class"),E17*IF(B17="Year 7",$C$3,$C$4),E17))) -> 1 | J17: A4 paper | K17: 1 | L17: =IF(OR(K17="",O17<>"",I17=""),"",ROUNDUP(I17*K17,0)) -> 1 | M17: Wall poster of every Year 7 frame with its Chinese and an example; Week 1 uses 'I observe ___.' and 'I infer ___ because ___.' | P17: No: paper printing | Q17: Teacher Guide Section 8 says print before Week 1; the Week 1 lesson file does not mention it.
A18: 1 | B18: Year 7 | C18: Printing (paper copies) | D18: Sentence frame bank cards, Ice Engineers | E18: 6 | F18: sets; 16 A6 cards per set, 4 cards per A4 sheet with cut lines (4 sheets per set) | G18: per group | I18: =IF(E18="","",IF(OR(AND(H18="Plan A",$C$5="B"),AND(H18="Plan B",$C$5="A")),0,IF(OR(G18="per student",G18="per group",G18="per class"),E18*IF(B18="Year 7",$C$3,$C$4),E18))) -> 6 | J18: A4 paper | K18: 4 | L18: =IF(OR(K18="",O18<>"",I18=""),"",ROUNDUP(I18*K18,0)) -> 24 | M18: One set per table so groups rehearse reports in English with the frame. | P18: No: paper printing | Q18: Paper or card is not stated (24 A4 sheets of card if card). The Week 1 lesson file does not mention them.
A19: 1 | B19: Year 7 | C19: Printing (paper copies) | D19: My Science Dictionary, Year 7 | E19: 28 | F19: booklets; A5 saddle-stitched, 24 pages (6 A4 sheets folded and stapled twice), 90 gsm (1 per student plus 4 spares) | G19: per student | I19: =IF(E19="","",IF(OR(AND(H19="Plan A",$C$5="B"),AND(H19="Plan B",$C$5="A")),0,IF(OR(G19="per student",G19="per group",G19="per class"),E19*IF(B19="Year 7",$C$3,$C$4),E19))) -> 28 | J19: Booklet (reprographics) | K19: 6 | L19: =IF(OR(K19="",O19<>"",I19=""),"",ROUNDUP(I19*K19,0)) -> 168 | M19: Handed out with the logbook; name and class on the cover; open in every lesson but closed and put away during the skills check; 4 spares kept with the logbook spares. | P19: Yes, see note | Q19: Goes to 28 pages (7 sheets each) if the entries need more room; the requisition row gives neither the page count nor 90 gsm. The dictionary file says hand out in Week 1 with the logbook; the language pack allows Week 1 or the next lesson.
A20: 1 | B20: Year 7 | C20: Printing (paper copies) | D20: Scientist's Logbook, Year 7 | E20: 24 | F20: booklets; A5, one page per week (page count not stated) | G20: per student | I20: =IF(E20="","",IF(OR(AND(H20="Plan A",$C$5="B"),AND(H20="Plan B",$C$5="A")),0,IF(OR(G20="per student",G20="per group",G20="per class"),E20*IF(B20="Year 7",$C$3,$C$4),E20))) -> 24 | J20: Booklet (reprographics) | L20: =IF(OR(K20="",O20<>"",I20=""),"",ROUNDUP(I20*K20,0)) | M20: First page written in Think and Reflect ('What I did', and 'New words' if time); collected into the class box at the end of every lesson. | P20: Yes | Q20: Page count, cover and binding are not stated; only one A5 page is designed. The dictionary file mentions 'logbook spares' but gives no number.
A21: 1 | B21: Year 7 | C21: Card, laminating and stationery | D21: Footprint puzzle stage cards (Stage 1, 2, 3) | E21: 6 | F21: sets of 3 A4 landscape cards; Cards 1 and 2 single-sided, Card 3 with the teacher note printed on the back | G21: per group | I21: =IF(E21="","",IF(OR(AND(H21="Plan A",$C$5="B"),AND(H21="Plan B",$C$5="A")),0,IF(OR(G21="per student",G21="per group",G21="per class"),E21*IF(B21="Year 7",$C$3,$C$4),E21))) -> 6 | J21: A4 card | K21: 3 | L21: =IF(OR(K21="",O21<>"",I21=""),"",ROUNDUP(I21*K21,0)) -> 18 | M21: Reveal cards for the 10-minute footprint puzzle, handed out stage by stage, returned in their envelopes and reused. | P21: Yes, see note | Q21: The requisition row (white card, 18 sheets) says single-sided, but the 6 copies of Card 3 carry the teacher note on the back. Card or laminated paper is allowed. Section 6a says 6 sets per class; as the cards come back to the teacher, one set might serve every class if lessons do not overlap (decide).
A22: 1 | B22: Year 7 | C22: Card, laminating and stationery | D22: Laminating pouches, A4, for puzzle cards (only if laminating paper instead of card) | E22: 18 | F22: pouches, A4 | G22: per group | I22: =IF(E22="","",IF(OR(AND(H22="Plan A",$C$5="B"),AND(H22="Plan B",$C$5="A")),0,IF(OR(G22="per student",G22="per group",G22="per class"),E22*IF(B22="Year 7",$C$3,$C$4),E22))) -> 18 | L22: =IF(OR(K22="",O22<>"",I22=""),"",ROUNDUP(I22*K22,0)) | M22: Alternative to card: print the 18 puzzle cards on paper and laminate them. | N22: Optional | P22: Yes, see note | Q22: Mentioned only inside the requisition's white card note, not counted as a row. Would also need 18 sheets of A4 paper in place of card.
A23: 1 | B23: Year 7 | C23: Card, laminating and stationery | D23: Laminating pouches, A4, for role cards | E23: 6 | F23: pouches, A4 | G23: per group | I23: =IF(E23="","",IF(OR(AND(H23="Plan A",$C$5="B"),AND(H23="Plan B",$C$5="A")),0,IF(OR(G23="per student",G23="per group",G23="per class"),E23*IF(B23="Year 7",$C$3,$C$4),E23))) -> 6 | L23: =IF(OR(K23="",O23<>"",I23=""),"",ROUNDUP(I23*K23,0)) | M23: Laminate the 6 role card sheets before cutting them into cards. | P23: Yes
A24: 1 | B24: Year 7 | C24: Card, laminating and stationery | D24: Laminating pouches, A5, for classroom language cards | E24: 30 | F24: pouches, A5 | G24: per student | I24: =IF(E24="","",IF(OR(AND(H24="Plan A",$C$5="B"),AND(H24="Plan B",$C$5="A")),0,IF(OR(G24="per student",G24="per group",G24="per class"),E24*IF(B24="Year 7",$C$3,$C$4),E24))) -> 30 | L24: =IF(OR(K24="",O24<>"",I24=""),"",ROUNDUP(I24*K24,0)) | M24: Laminate the 30 two-sided classroom language cards. | P24: Yes
A25: 1 | B25: Year 7 | C25: Card, laminating and stationery | D25: Envelopes for the puzzle stages | E25: 18 | F25: envelopes, A4 size (C4, hold an A4 card flat) | G25: per group | I25: =IF(E25="","",IF(OR(AND(H25="Plan A",$C$5="B"),AND(H25="Plan B",$C$5="A")),0,IF(OR(G25="per student",G25="per group",G25="per class"),E25*IF(B25="Year 7",$C$3,$C$4),E25))) -> 18 | L25: =IF(OR(K25="",O25<>"",I25=""),"",ROUNDUP(I25*K25,0)) | M25: 3 per group labelled Stage 1, Stage 2, Stage 3; Stage 2 and 3 kept on the teacher desk; returned at clean-up and reused. | P25: Yes | Q25: The lesson file gives no size; the requisition lists A4 (C4) envelopes.
A26: 1 | B26: Year 7 | C26: Card, laminating and stationery | D26: Name cards | E26: 24 | F26: cards | G26: per student | I26: =IF(E26="","",IF(OR(AND(H26="Plan A",$C$5="B"),AND(H26="Plan B",$C$5="A")),0,IF(OR(G26="per student",G26="per group",G26="per class"),E26*IF(B26="Year 7",$C$3,$C$4),E26))) -> 24 | L26: =IF(OR(K26="",O26<>"",I26=""),"",ROUNDUP(I26*K26,0)) | M26: One per student, set out on the tables by the group seating plan before students arrive (Slide 1: 'Find your name card'). | P26: Yes | Q26: No design, size or material is given.
A27: 1 | B27: Year 7 | C27: Card, laminating and stationery | D27: Pencils | E27: 24 | F27: pencils, HB | G27: per student | I27: =IF(E27="","",IF(OR(AND(H27="Plan A",$C$5="B"),AND(H27="Plan B",$C$5="A")),0,IF(OR(G27="per student",G27="per group",G27="per class"),E27*IF(B27="Year 7",$C$3,$C$4),E27))) -> 24 | L27: =IF(OR(K27="",O27<>"",I27=""),"",ROUNDUP(I27*K27,0)) | M27: One per student for the skills check, survey, worksheet and logbook. | P27: Yes, see note | Q27: The requisition counts 24 HB; the teacher-desk spares have no number.
A28: 1 | B28: Year 7 | C28: Equipment and materials | D28: Class box | E28: 1 | F28: box with lid | G28: per class | I28: =IF(E28="","",IF(OR(AND(H28="Plan A",$C$5="B"),AND(H28="Plan B",$C$5="A")),0,IF(OR(G28="per student",G28="per group",G28="per class"),E28*IF(B28="Year 7",$C$3,$C$4),E28))) -> 1 | L28: =IF(OR(K28="",O28<>"",I28=""),"",ROUNDUP(I28*K28,0)) | M28: Logbooks are collected into it at the end of every lesson and kept there all term. | P28: Yes | Q28: The kind of box is not stated; the requisition chooses a plastic storage box with lid.
A29: 1 | B29: Year 7 | C29: Equipment and materials | D29: Class assessment folder | E29: 1 | F29: folder | G29: per class | I29: =IF(E29="","",IF(OR(AND(H29="Plan A",$C$5="B"),AND(H29="Plan B",$C$5="A")),0,IF(OR(G29="per student",G29="per group",G29="per class"),E29*IF(B29="Year 7",$C$3,$C$4),E29))) -> 1 | L29: =IF(OR(K29="",O29<>"",I29=""),"",ROUNDUP(I29*K29,0)) | M29: Marked Week 1 skills check papers are filed here and not returned until after Week 10. | P29: No: may already exist | Q29: Not in the requisition; check whether each class already has one.
A30: 1 | B30: Year 7 | C30: Equipment and materials | D30: Laminator and guillotine (or scissors) | F30: not stated (access needed); access to equipment | G30: per once | I30: =IF(E30="","",IF(OR(AND(H30="Plan A",$C$5="B"),AND(H30="Plan B",$C$5="A")),0,IF(OR(G30="per student",G30="per group",G30="per class"),E30*IF(B30="Year 7",$C$3,$C$4),E30))) | L30: =IF(OR(K30="",O30<>"",I30=""),"",ROUNDUP(I30*K30,0)) | M30: Laminate the role cards and classroom language cards; cut the role cards, frame cards and surveys. | P30: No: tool | Q30: Named nowhere; the specs only say laminate and cut.
A31: 1 | B31: Year 7 | C31: Equipment and materials | D31: Rulers (to measure against the 10 cm scale bar on the puzzle cards) | F31: not stated; rulers | G31: per group | I31: =IF(E31="","",IF(OR(AND(H31="Plan A",$C$5="B"),AND(H31="Plan B",$C$5="A")),0,IF(OR(G31="per student",G31="per group",G31="per class"),E31*IF(B31="Year 7",$C$3,$C$4),E31))) | L31: =IF(OR(K31="",O31<>"",I31=""),"",ROUNDUP(I31*K31,0)) | M31: Card 1 asks students to 'Count and measure'; every card has a 10 cm scale bar and the model answers give distances in cm. | N31: Optional | P31: No: may already exist | Q31: Not on the kit card; students can estimate by eye against the scale bar. Decide whether to put one on each table.
A32: 1 | B32: Year 7 | C32: Make beforehand | D32: Footprint puzzle envelope sets | E32: 6 | F32: sets of 3 labelled envelopes, one stage card in each | G32: per group | I32: =IF(E32="","",IF(OR(AND(H32="Plan A",$C$5="B"),AND(H32="Plan B",$C$5="A")),0,IF(OR(G32="per student",G32="per group",G32="per class"),E32*IF(B32="Year 7",$C$3,$C$4),E32))) -> 6 | L32: =IF(OR(K32="",O32<>"",I32=""),"",ROUNDUP(I32*K32,0)) | M32: Lead Scientists collect Stage 1; the 12 Stage 2 and 3 envelopes stay on the teacher desk until about 3 and 6 minutes into Do. | P32: Yes, see note | Q32: Made from the puzzle card and envelope rows; nothing extra to order.
A33: 1 | B33: Year 7 | C33: Make beforehand | D33: Group seating plan (with starting roles) | E33: 1 | F33: plan | G33: per class | I33: =IF(E33="","",IF(OR(AND(H33="Plan A",$C$5="B"),AND(H33="Plan B",$C$5="A")),0,IF(OR(G33="per student",G33="per group",G33="per class"),E33*IF(B33="Year 7",$C$3,$C$4),E33))) -> 1 | L33: =IF(OR(K33="",O33<>"",I33=""),"",ROUNDUP(I33*K33,0)) | M33: Six groups of 3 or 4 seated from the first minute; each Band 1 student beside a Band 3 language buddy; groups stay the same for Weeks 1 to 5. | P33: No: paper printing | Q33: Teacher-made; nothing to order. Language bands are only recorded after Weeks 1 to 2; decide how Band 1 students are identified for the Week 1 plan.
A34: 1 | B34: Year 8 | C34: Printing (paper copies) | D34: Skills Check paper, Year 8 (The Missing Trophy), Week 1 baseline | E34: 24 | F34: copies; 5 A4 portrait pages, double-sided (last side blank) | G34: per student | I34: =IF(E34="","",IF(OR(AND(H34="Plan A",$C$5="B"),AND(H34="Plan B",$C$5="A")),0,IF(OR(G34="per student",G34="per group",G34="per class"),E34*IF(B34="Year 7",$C$3,$C$4),E34))) -> 24 | J34: A4 paper | K34: 3 | L34: =IF(OR(K34="",O34<>"",I34=""),"",ROUNDUP(I34*K34,0)) -> 72 | M34: 15-minute baseline done alone; collected at once, marked, entered in the tracker and filed, never returned before Week 10. | P34: No: paper printing | Q34: The written spec says two sides of A4 (1 sheet), but the designed paper has 5 pages ('Page 1 of 5'). Confirm which is final before printing (24 or 72 sheets). Print from the same frozen master that Week 10 will use.
A35: 1 | B35: Year 8 | C35: Printing (paper copies) | D35: Interest survey (half A4, two copies per A4 sheet with a cut line) | E35: 24 | F35: copies; half A4, 2 per A4 sheet, single-sided, cut in half | G35: per student | I35: =IF(E35="","",IF(OR(AND(H35="Plan A",$C$5="B"),AND(H35="Plan B",$C$5="A")),0,IF(OR(G35="per student",G35="per group",G35="per class"),E35*IF(B35="Year 7",$C$3,$C$4),E35))) -> 24 | J35: A4 paper | K35: 0.5 | L35: =IF(OR(K35="",O35<>"",I35=""),"",ROUNDUP(I35*K35,0)) -> 12 | M35: 3-minute six-statement smiley survey straight after the skills check; scores go into tracker W1 S1 to S6. | P35: No: paper printing
A36: 1 | B36: Year 8 | C36: Printing (paper copies) | D36: Worksheet: Think like a detective | E36: 24 | F36: copies; 3 A4 portrait pages: pages 1 and 2 double-sided, page 3 single-sided | G36: per student | I36: =IF(E36="","",IF(OR(AND(H36="Plan A",$C$5="B"),AND(H36="Plan B",$C$5="A")),0,IF(OR(G36="per student",G36="per group",G36="per class"),E36*IF(B36="Year 7",$C$3,$C$4),E36))) -> 24 | J36: A4 paper | K36: 2 | L36: =IF(OR(K36="",O36<>"",I36=""),"",ROUNDUP(I36*K36,0)) -> 48 | M36: Core O or I sort, Stretch, Challenge, My thinking, fold-under word bank and exit ticket strip; goes into the case file and the exit ticket is cut off and collected. | P36: No: paper printing | Q36: Sidedness not stated. Keep page 3 (exit ticket strip and fold-under word bank) on its own sheet so cutting off the strip does not cut page 2.
A37: 1 | B37: Year 8 | C37: Printing (paper copies) | D37: Case briefing and Lab 3 sign-in sheet | E37: 24 | F37: copies; 2 A4 portrait pages, double-sided | G37: per student | I37: =IF(E37="","",IF(OR(AND(H37="Plan A",$C$5="B"),AND(H37="Plan B",$C$5="A")),0,IF(OR(G37="per student",G37="per group",G37="per class"),E37*IF(B37="Year 7",$C$3,$C$4),E37))) -> 24 | J37: A4 paper | K37: 1 | L37: =IF(OR(K37="",O37<>"",I37=""),"",ROUNDUP(I37*K37,0)) -> 24 | M37: What happened, the note, the five evidence items and the sign-in sheet; second item in the case file. | P37: No: paper printing | Q37: Lesson file 6.2 describes one page, but the design has two ('Page 1 of 2, turn over'). Double-sided keeps it to one sheet.
A38: 1 | B38: Year 8 | C38: Printing (paper copies) | D38: Scene map, Lab 3 (A4 landscape) | E38: 24 | F38: copies; 1 A4 landscape page, single-sided | G38: per student | I38: =IF(E38="","",IF(OR(AND(H38="Plan A",$C$5="B"),AND(H38="Plan B",$C$5="A")),0,IF(OR(G38="per student",G38="per group",G38="per class"),E38*IF(B38="Year 7",$C$3,$C$4),E38))) -> 24 | J38: A4 paper | K38: 1 | L38: =IF(OR(K38="",O38<>"",I38=""),"",ROUNDUP(I38*K38,0)) -> 24 | M38: Top-down plan of Lab 3 on the lettered grid for the Do task; third item in the case file. | P38: No: paper printing
A39: 1 | B39: Year 8 | C39: Printing (paper copies) | D39: Scene map, enlarged wall copy | E39: 1 | F39: copy; A3, single-sided | G39: per room | I39: =IF(E39="","",IF(OR(AND(H39="Plan A",$C$5="B"),AND(H39="Plan B",$C$5="A")),0,IF(OR(G39="per student",G39="per group",G39="per class"),E39*IF(B39="Year 7",$C$3,$C$4),E39))) -> 1 | J39: A3 paper | K39: 1 | L39: =IF(OR(K39="",O39<>"",I39=""),"",ROUNDUP(I39*K39,0)) -> 1 | M39: Wall copy; Band 1 students point to a square on it for the exit ticket. | P39: Yes | Q39: 1 of the 4 sheets in the 'A3 printing' row.
A40: 1 | B40: Year 8 | C40: Printing (paper copies) | D40: Suspect profile cards (four A6 cards on one A4 sheet, cut lines) | E40: 24 | F40: copies; 1 A4 portrait sheet, single-sided | G40: per student | I40: =IF(E40="","",IF(OR(AND(H40="Plan A",$C$5="B"),AND(H40="Plan B",$C$5="A")),0,IF(OR(G40="per student",G40="per group",G40="per class"),E40*IF(B40="Year 7",$C$3,$C$4),E40))) -> 24 | J40: A4 paper | K40: 1 | L40: =IF(OR(K40="",O40<>"",I40=""),"",ROUNDUP(I40*K40,0)) -> 24 | M40: Meet the suspects; the Week 2 Do Now uses them, so every case file needs a set; students may cut them out. | P40: No: paper printing
A41: 1 | B41: Year 8 | C41: Printing (paper copies) | D41: Kit card, teacher copy | E41: 1 | F41: copy; A5 (half A4), single-sided | G41: per once | I41: =IF(E41="","",IF(OR(AND(H41="Plan A",$C$5="B"),AND(H41="Plan B",$C$5="A")),0,IF(OR(G41="per student",G41="per group",G41="per class"),E41*IF(B41="Year 7",$C$3,$C$4),E41))) -> 1 | J41: A5 paper | K41: 1 | L41: =IF(OR(K41="",O41<>"",I41=""),"",ROUNDUP(I41*K41,0)) -> 1 | M41: Kit, prep, hazards and clean-up checklist for the teacher. | P41: No: paper printing
A42: 1 | B42: Year 8 | C42: Printing (paper copies) | D42: Skills Check mark scheme, teacher copy | E42: 1 | F42: copy; 2 A4 pages, double-sided | G42: per once | I42: =IF(E42="","",IF(OR(AND(H42="Plan A",$C$5="B"),AND(H42="Plan B",$C$5="A")),0,IF(OR(G42="per student",G42="per group",G42="per class"),E42*IF(B42="Year 7",$C$3,$C$4),E42))) -> 1 | J42: A4 paper | K42: 1 | L42: =IF(OR(K42="",O42<>"",I42=""),"",ROUNDUP(I42*K42,0)) -> 1 | M42: Marking the baseline papers within the week; no half marks; Chinese answers accepted. | P42: No: paper printing | Q42: Sidedness not stated; double-sided assumed.
A43: 1 | B43: Year 8 | C43: Printing (paper copies) | D43: Teacher Pre-test Record: pens A to D | E43: 1 | F43: copy; 1 A4 portrait page, single-sided | G43: per once | I43: =IF(E43="","",IF(OR(AND(H43="Plan A",$C$5="B"),AND(H43="Plan B",$C$5="A")),0,IF(OR(G43="per student",G43="per group",G43="per class"),E43*IF(B43="Year 7",$C$3,$C$4),E43))) -> 1 | J43: A4 paper | K43: 1 | L43: =IF(OR(K43="",O43<>"",I43=""),"",ROUNDUP(I43*K43,0)) -> 1 | M43: Record the real chromatography results of pens A to D in the pen pre-test; kept in the teacher folder with the dried strips. | P43: No: paper printing | Q43: Designed in the Week 3 file, Section 6.2 ('Print: 1'), but the pre-test runs in the Week 1 week, so print it now. Count it once if the Week 3 list also includes it.
A44: 1 | B44: Year 8 | C44: Printing (paper copies) | D44: Scene table sign: EVIDENCE: DO NOT TOUCH | E44: 1 | F44: copy; A5 landscape, single-sided | G44: per class | I44: =IF(E44="","",IF(OR(AND(H44="Plan A",$C$5="B"),AND(H44="Plan B",$C$5="A")),0,IF(OR(G44="per student",G44="per group",G44="per class"),E44*IF(B44="Year 7",$C$3,$C$4),E44))) -> 1 | J44: A5 paper | K44: 1 | L44: =IF(OR(K44="",O44<>"",I44=""),"",ROUNDUP(I44*K44,0)) -> 1 | M44: Look-only sign for the optional scene table. | N44: Optional | P44: No: paper printing
A45: 1 | B45: Year 8 | C45: Printing (paper copies) | D45: Scene footprint, true size (24 cm long) | E45: 1 | F45: print; A4 portrait at 100% scale, single-sided | G45: per class | I45: =IF(E45="","",IF(OR(AND(H45="Plan A",$C$5="B"),AND(H45="Plan B",$C$5="A")),0,IF(OR(G45="per student",G45="per group",G45="per class"),E45*IF(B45="Year 7",$C$3,$C$4),E45))) -> 1 | J45: A4 paper | K45: 1 | L45: =IF(OR(K45="",O45<>"",I45=""),"",ROUNDUP(I45*K45,0)) -> 1 | M45: Paper footprint for the optional scene table. | N45: Optional | P45: Yes | Q45: Print at actual size, never fit to page, and check it measures 24 cm with a ruler.
A46: 1 | B46: Year 8 | C46: Printing (paper copies) | D46: Instruction words key poster (A3 landscape) | E46: 1 | F46: poster; A3, single-sided | G46: per room | I46: =IF(E46="","",IF(OR(AND(H46="Plan A",$C$5="B"),AND(H46="Plan B",$C$5="A")),0,IF(OR(G46="per student",G46="per group",G46="per class"),E46*IF(B46="Year 7",$C$3,$C$4),E46))) -> 1 | J46: A3 paper | K46: 1 | L46: =IF(OR(K46="",O46<>"",I46=""),"",ROUNDUP(I46*K46,0)) -> 1 | M46: Wall key of task words with icons; may stay up during the skills check; used all term. | P46: Yes | Q46: 1 of the 4 sheets in the 'A3 printing' row. One per room: if Year 7 and Year 8 share a room, one set of the three A3 posters serves both.
A47: 1 | B47: Year 8 | C47: Printing (paper copies) | D47: Classroom language poster, side B (A3) | E47: 1 | F47: poster; A3, single-sided | G47: per room | I47: =IF(E47="","",IF(OR(AND(H47="Plan A",$C$5="B"),AND(H47="Plan B",$C$5="A")),0,IF(OR(G47="per student",G47="per group",G47="per class"),E47*IF(B47="Year 7",$C$3,$C$4),E47))) -> 1 | J47: A3 paper | K47: 1 | L47: =IF(OR(K47="",O47<>"",I47=""),"",ROUNDUP(I47*K47,0)) -> 1 | M47: Wall copy of the 'how to ask for help' phrases; used all term. | P47: Yes | Q47: 1 of the 4 sheets in the 'A3 printing' row.
A48: 1 | B48: Year 8 | C48: Printing (paper copies) | D48: Think in any language poster (A3 portrait) | E48: 1 | F48: poster; A3, single-sided | G48: per room | I48: =IF(E48="","",IF(OR(AND(H48="Plan A",$C$5="B"),AND(H48="Plan B",$C$5="A")),0,IF(OR(G48="per student",G48="per group",G48="per class"),E48*IF(B48="Year 7",$C$3,$C$4),E48))) -> 1 | J48: A3 paper | K48: 1 | L48: =IF(OR(K48="",O48<>"",I48=""),"",ROUNDUP(I48*K48,0)) -> 1 | M48: Wall reminder that the science, not the English, is judged; used all term. | P48: Yes | Q48: 1 of the 4 sheets in the 'A3 printing' row.
A49: 1 | B49: Year 8 | C49: Printing (paper copies) | D49: Sentence frame poster, Science Detectives (A4 portrait) | E49: 1 | F49: poster; 1 A4 page, single-sided | G49: per room | I49: =IF(E49="","",IF(OR(AND(H49="Plan A",$C$5="B"),AND(H49="Plan B",$C$5="A")),0,IF(OR(G49="per student",G49="per group",G49="per class"),E49*IF(B49="Year 7",$C$3,$C$4),E49))) -> 1 | J49: A4 paper | K49: 1 | L49: =IF(OR(K49="",O49<>"",I49=""),"",ROUNDUP(I49*K49,0)) -> 1 | M49: Wall bank of every Year 8 frame with Chinese and an example, including today's three frames. | P49: No: paper printing
A50: 1 | B50: Year 8 | C50: Printing (paper copies) | D50: Sentence frame cards, Science Detectives (A6, four per A4 sheet) | E50: 6 | F50: sets; 15 cards per set on 4 A4 sheets (last sheet 3 cards), single-sided, cut | G50: per group | I50: =IF(E50="","",IF(OR(AND(H50="Plan A",$C$5="B"),AND(H50="Plan B",$C$5="A")),0,IF(OR(G50="per student",G50="per group",G50="per class"),E50*IF(B50="Year 7",$C$3,$C$4),E50))) -> 6 | J50: A4 paper | K50: 4 | L50: =IF(OR(K50="",O50<>"",I50=""),"",ROUNDUP(I50*K50,0)) -> 24 | M50: One set on each group table for rehearsing answers in English; used all term. | P50: No: paper printing | Q50: Paper, card or laminated is not stated; no requisition row covers card or pouches for these.
A51: 1 | B51: Year 8 | C51: Printing (paper copies) | D51: My Science Dictionary, Year 8 (A5 booklet, saddle-stitched) | E51: 28 | F51: booklets; 28 A5 pages = 7 A4 sheets double-sided, folded and stapled, 90 gsm | G51: per student | I51: =IF(E51="","",IF(OR(AND(H51="Plan A",$C$5="B"),AND(H51="Plan B",$C$5="A")),0,IF(OR(G51="per student",G51="per group",G51="per class"),E51*IF(B51="Year 7",$C$3,$C$4),E51))) -> 28 | J51: A4 90 gsm (booklet) | K51: 7 | L51: =IF(OR(K51="",O51<>"",I51=""),"",ROUNDUP(I51*K51,0)) -> 196 | M51: Key word booklet tucked into each case file in Week 1; closed during the skills check; the student's to keep. | P51: No: add | Q51: 1 per student plus 4 spares (stated). Spec says 32 pages (8 sheets); the designed Year 8 booklet has 28 pages (7 sheets). Year 7 has a dictionary row; Year 8 does not.
A52: 1 | B52: Year 8 | C52: Printing (paper copies) | D52: Scientist's Logbook (A5 booklet, one page per week) | E52: 24 | F52: booklets; A5, page count not stated | G52: per student | I52: =IF(E52="","",IF(OR(AND(H52="Plan A",$C$5="B"),AND(H52="Plan B",$C$5="A")),0,IF(OR(G52="per student",G52="per group",G52="per class"),E52*IF(B52="Year 7",$C$3,$C$4),E52))) -> 24 | J52: Booklet (reprographics) | L52: =IF(OR(K52="",O52<>"",I52=""),"",ROUNDUP(I52*K52,0)) | M52: One line under 'What I found' if time allows at the end of Think and Reflect (otherwise the evidence log row counts); kept in the class box. | P52: No: add | Q52: Every student keeps one; the Teacher Guide says print logbooks before Week 1. Page count and paper not stated. Year 7 has a logbook row; Year 8 does not, though the class box row mentions logbooks.
A53: 1 | B53: Year 8 | C53: Card, laminating and stationery | D53: Case file cover (on card if possible) | E53: 24 | F53: copies; A4 portrait, single-sided | G53: per student | I53: =IF(E53="","",IF(OR(AND(H53="Plan A",$C$5="B"),AND(H53="Plan B",$C$5="A")),0,IF(OR(G53="per student",G53="per group",G53="per class"),E53*IF(B53="Year 7",$C$3,$C$4),E53))) -> 24 | J53: A4 card | K53: 1 | L53: =IF(OR(K53="",O53<>"",I53=""),"",ROUNDUP(I53*K53,0)) -> 24 | M53: Front of each case file with detective name, class, group and role fields. | P53: Yes | Q53: 24 of the 49 sheets in the 'White card, A4' row.
A54: 1 | B54: Year 8 | C54: Card, laminating and stationery | D54: Evidence log (on card if possible) | E54: 24 | F54: copies; A4 landscape, single-sided | G54: per student | I54: =IF(E54="","",IF(OR(AND(H54="Plan A",$C$5="B"),AND(H54="Plan B",$C$5="A")),0,IF(OR(G54="per student",G54="per group",G54="per class"),E54*IF(B54="Year 7",$C$3,$C$4),E54))) -> 24 | J54: A4 card | K54: 1 | L54: =IF(OR(K54="",O54<>"",I54=""),"",ROUNDUP(I54*K54,0)) -> 24 | M54: Evidence table, suspect tracker and confidence rows; stays in the case file all ten weeks; row 1 today or in the Week 2 Do Now. | P54: Yes | Q54: 24 of the 49 sheets in the 'White card, A4' row.
A55: 1 | B55: Year 8 | C55: Card, laminating and stationery | D55: Plain white card for the note prop | E55: 1 | F55: A4 sheet | G55: per once | I55: =IF(E55="","",IF(OR(AND(H55="Plan A",$C$5="B"),AND(H55="Plan B",$C$5="A")),0,IF(OR(G55="per student",G55="per group",G55="per class"),E55*IF(B55="Year 7",$C$3,$C$4),E55))) -> 1 | J55: A4 card | K55: 1 | L55: =IF(OR(K55="",O55<>"",I55=""),"",ROUNDUP(I55*K55,0)) -> 1 | M55: The handwritten note is written on it with pen B. | P55: Yes | Q55: 1 of the 49 sheets in the 'White card, A4' row.
A56: 1 | B56: Year 8 | C56: Card, laminating and stationery | D56: Group role cards with duties (6 business-card cards per A4 sheet) | E56: 6 | F56: sets; 1 A4 sheet per set, single-sided, laminated then cut | G56: per group | I56: =IF(E56="","",IF(OR(AND(H56="Plan A",$C$5="B"),AND(H56="Plan B",$C$5="A")),0,IF(OR(G56="per student",G56="per group",G56="per class"),E56*IF(B56="Year 7",$C$3,$C$4),E56))) -> 6 | J56: A4 paper | K56: 1 | L56: =IF(OR(K56="",O56<>"",I56=""),"",ROUNDUP(I56*K56,0)) -> 6 | M56: Role cards on every table (Lead Scientist, Measurer, Recorder, Safety Officer, Reporter, Language buddy); the case file cover asks for 'My role this week'. | P56: No: paper printing | Q56: Paper or card before laminating is not stated. The pouches are a separate row.
A57: 1 | B57: Year 8 | C57: Card, laminating and stationery | D57: Classroom language card (A5 landscape, two-sided, laminated) | E57: 30 | F57: cards; A5, double-sided (sides A and B) | G57: per student | I57: =IF(E57="","",IF(OR(AND(H57="Plan A",$C$5="B"),AND(H57="Plan B",$C$5="A")),0,IF(OR(G57="per student",G57="per group",G57="per class"),E57*IF(B57="Year 7",$C$3,$C$4),E57))) -> 30 | J57: A5 paper | K57: 1 | L57: =IF(OR(K57="",O57<>"",I57=""),"",ROUNDUP(I57*K57,0)) -> 30 | M57: Teacher routine phrases and student help phrases at every desk; used all term. | P57: No: paper printing | Q57: 1 per student plus 6 spares (stated). Paper or card, and whether printed 2 per A4 sheet, are not stated.
A58: 1 | B58: Year 8 | C58: Card, laminating and stationery | D58: Laminating pouches, A4 | E58: 6 | F58: pouches | G58: per class | I58: =IF(E58="","",IF(OR(AND(H58="Plan A",$C$5="B"),AND(H58="Plan B",$C$5="A")),0,IF(OR(G58="per student",G58="per group",G58="per class"),E58*IF(B58="Year 7",$C$3,$C$4),E58))) -> 6 | L58: =IF(OR(K58="",O58<>"",I58=""),"",ROUNDUP(I58*K58,0)) | M58: Laminating the six role card sheets. | P58: Yes
A59: 1 | B59: Year 8 | C59: Card, laminating and stationery | D59: Laminating pouches, A5 | E59: 30 | F59: pouches | G59: per class | I59: =IF(E59="","",IF(OR(AND(H59="Plan A",$C$5="B"),AND(H59="Plan B",$C$5="A")),0,IF(OR(G59="per student",G59="per group",G59="per class"),E59*IF(B59="Year 7",$C$3,$C$4),E59))) -> 30 | L59: =IF(OR(K59="",O59<>"",I59=""),"",ROUNDUP(I59*K59,0)) | M59: Laminating the classroom language cards. | P59: Yes
A60: 1 | B60: Year 8 | C60: Card, laminating and stationery | D60: A4 folders for case files | E60: 24 | F60: folders | G60: per student | I60: =IF(E60="","",IF(OR(AND(H60="Plan A",$C$5="B"),AND(H60="Plan B",$C$5="A")),0,IF(OR(G60="per student",G60="per group",G60="per class"),E60*IF(B60="Year 7",$C$3,$C$4),E60))) -> 24 | L60: =IF(OR(K60="",O60<>"",I60=""),"",ROUNDUP(I60*K60,0)) | M60: Hold the cover, briefing, scene map, suspect cards, evidence log, worksheet and dictionary for all ten weeks; assessed in Week 10. | P60: Yes
A61: 1 | B61: Year 8 | C61: Card, laminating and stationery | D61: Pencils | E61: 24 | F61: pencils | G61: per student | I61: =IF(E61="","",IF(OR(AND(H61="Plan A",$C$5="B"),AND(H61="Plan B",$C$5="A")),0,IF(OR(G61="per student",G61="per group",G61="per class"),E61*IF(B61="Year 7",$C$3,$C$4),E61))) -> 24 | L61: =IF(OR(K61="",O61<>"",I61=""),"",ROUNDUP(I61*K61,0)) | M61: Skills check, survey, worksheet and exit ticket. | P61: Yes
A62: 1 | B62: Year 8 | C62: Card, laminating and stationery | D62: Name cards | F62: not stated (24, one per student, is the requisition's assumption); cards | G62: per student | I62: =IF(E62="","",IF(OR(AND(H62="Plan A",$C$5="B"),AND(H62="Plan B",$C$5="A")),0,IF(OR(G62="per student",G62="per group",G62="per class"),E62*IF(B62="Year 7",$C$3,$C$4),E62))) | L62: =IF(OR(K62="",O62<>"",I62=""),"",ROUNDUP(I62*K62,0)) | M62: Seat students in fixed groups of 4 from the first minute, with each Band 1 student beside a Band 3 buddy. | P62: Yes, see note | Q62: Kit card says 'Set out groups of 4 with name cards' but gives no number or material. Confirm 24 and whether on card.
A63: 1 | B63: Year 8 | C63: Card, laminating and stationery | D63: Masking tape | F63: not stated (enough to cover the brand names on 8 pens; the requisition orders 1 roll); roll | G63: per once | I63: =IF(E63="","",IF(OR(AND(H63="Plan A",$C$5="B"),AND(H63="Plan B",$C$5="A")),0,IF(OR(G63="per student",G63="per group",G63="per class"),E63*IF(B63="Year 7",$C$3,$C$4),E63))) | L63: =IF(OR(K63="",O63<>"",I63=""),"",ROUNDUP(I63*K63,0)) | M63: Cover each pen's brand name and write the letter A to D on the tape. | P63: Yes, see note | Q63: The sources give no amount; 1 roll is the requisition's figure.
A64: 1 | B64: Year 8 | C64: Card, laminating and stationery | D64: Class assessment folder | E64: 1 | F64: folder | G64: per class | I64: =IF(E64="","",IF(OR(AND(H64="Plan A",$C$5="B"),AND(H64="Plan B",$C$5="A")),0,IF(OR(G64="per student",G64="per group",G64="per class"),E64*IF(B64="Year 7",$C$3,$C$4),E64))) -> 1 | L64: =IF(OR(K64="",O64<>"",I64=""),"",ROUNDUP(I64*K64,0)) | M64: File the marked skills checks, which are not returned before Week 10. | P64: No: may already exist | Q64: Not in the requisition; check whether one exists.
A65: 1 | B65: Year 8 | C65: Equipment and materials | D65: Black washable (water-based) felt-tip pens, four different brands, two of each | E65: 8 | F65: pens | G65: per once | I65: =IF(E65="","",IF(OR(AND(H65="Plan A",$C$5="B"),AND(H65="Plan B",$C$5="A")),0,IF(OR(G65="per student",G65="per group",G65="per class"),E65*IF(B65="Year 7",$C$3,$C$4),E65))) -> 8 | L65: =IF(OR(K65="",O65<>"",I65=""),"",ROUNDUP(I65*K65,0)) | M65: Pen pre-test pens labelled A to D (one spare of each); pen B writes the note; reused in Week 3. | P65: Yes | Q65: Not permanent markers; their ink will not move with water.
A66: 1 | B66: Year 8 | C66: Equipment and materials | D66: Cups for the pen pre-test | E66: 4 | F66: cups | G66: per once | I66: =IF(E66="","",IF(OR(AND(H66="Plan A",$C$5="B"),AND(H66="Plan B",$C$5="A")),0,IF(OR(G66="per student",G66="per group",G66="per class"),E66*IF(B66="Year 7",$C$3,$C$4),E66))) -> 4 | L66: =IF(OR(K66="",O66<>"",I66=""),"",ROUNDUP(I66*K66,0)) | M66: Each coffee-filter strip stands in a cup with water 1 cm deep, below the ink dot. | P66: Yes
A67: 1 | B67: Year 8 | C67: Equipment and materials | D67: Class box for case files | E67: 1 | F67: box | G67: per class | I67: =IF(E67="","",IF(OR(AND(H67="Plan A",$C$5="B"),AND(H67="Plan B",$C$5="A")),0,IF(OR(G67="per student",G67="per group",G67="per class"),E67*IF(B67="Year 7",$C$3,$C$4),E67))) -> 1 | L67: =IF(OR(K67="",O67<>"",I67=""),"",ROUNDUP(I67*K67,0)) | M67: Case files, filed by group, and logbooks stay in it between lessons. | P67: Yes
A68: 1 | B68: Year 8 | C68: Equipment and materials | D68: Drinking glass | E68: 1 | F68: glass | G68: per class | I68: =IF(E68="","",IF(OR(AND(H68="Plan A",$C$5="B"),AND(H68="Plan B",$C$5="A")),0,IF(OR(G68="per student",G68="per group",G68="per class"),E68*IF(B68="Year 7",$C$3,$C$4),E68))) -> 1 | L68: =IF(OR(K68="",O68<>"",I68=""),"",ROUNDUP(I68*K68,0)) | M68: Scene table copy of evidence 2. | N68: Optional | P68: Yes
A69: 1 | B69: Year 8 | C69: Equipment and materials | D69: Dark tray | E69: 1 | F69: tray | G69: per class | I69: =IF(E69="","",IF(OR(AND(H69="Plan A",$C$5="B"),AND(H69="Plan B",$C$5="A")),0,IF(OR(G69="per student",G69="per group",G69="per class"),E69*IF(B69="Year 7",$C$3,$C$4),E69))) -> 1 | L69: =IF(OR(K69="",O69<>"",I69=""),"",ROUNDUP(I69*K69,0)) | M69: Holds the teaspoon of baking soda (evidence 3) on the scene table, so the white powder shows. | N69: Optional | P69: Yes | Q69: The requisition row is named 'Trays'; its note asks for the dark tray.
A70: 1 | B70: Year 8 | C70: Equipment and materials | D70: Saucer | E70: 1 | F70: saucer | G70: per class | I70: =IF(E70="","",IF(OR(AND(H70="Plan A",$C$5="B"),AND(H70="Plan B",$C$5="A")),0,IF(OR(G70="per student",G70="per group",G70="per class"),E70*IF(B70="Year 7",$C$3,$C$4),E70))) -> 1 | L70: =IF(OR(K70="",O70<>"",I70=""),"",ROUNDUP(I70*K70,0)) | M70: Holds the scene liquid (evidence 4) on the scene table. | N70: Optional | P70: Yes
A71: 1 | B71: Year 8 | C71: Equipment and materials | D71: Scissors or guillotine | F71: not stated; tools | G71: per room | I71: =IF(E71="","",IF(OR(AND(H71="Plan A",$C$5="B"),AND(H71="Plan B",$C$5="A")),0,IF(OR(G71="per student",G71="per group",G71="per class"),E71*IF(B71="Year 7",$C$3,$C$4),E71))) | L71: =IF(OR(K71="",O71<>"",I71=""),"",ROUNDUP(I71*K71,0)) | M71: Cutting coffee-filter strips, survey halves, role cards and frame cards; the exit ticket strip has a cut line and students may cut out the suspect cards. | P71: No: tool | Q71: No source lists them, and the kit card gives groups none; decide who cuts off the exit ticket strips.
A72: 1 | B72: Year 8 | C72: Equipment and materials | D72: Laminator | F72: not stated; laminator | G72: per room | I72: =IF(E72="","",IF(OR(AND(H72="Plan A",$C$5="B"),AND(H72="Plan B",$C$5="A")),0,IF(OR(G72="per student",G72="per group",G72="per class"),E72*IF(B72="Year 7",$C$3,$C$4),E72))) | L72: =IF(OR(K72="",O72<>"",I72=""),"",ROUNDUP(I72*K72,0)) | M72: Laminating the role cards and classroom language cards. | P72: No: tool | Q72: No source lists it; check one is available.
A73: 1 | B73: Year 8 | C73: Equipment and materials | D73: Ruler and pencil (teacher prep) | F73: not stated; ruler and pencil | G73: per once | I73: =IF(E73="","",IF(OR(AND(H73="Plan A",$C$5="B"),AND(H73="Plan B",$C$5="A")),0,IF(OR(G73="per student",G73="per group",G73="per class"),E73*IF(B73="Year 7",$C$3,$C$4),E73))) | L73: =IF(OR(K73="",O73<>"",I73=""),"",ROUNDUP(I73*K73,0)) | M73: Measure the 2 cm by 10 cm pre-test strips, draw the pencil line 2 cm from the bottom, and check the paper footprint measures 24 cm. | P73: No: tool | Q73: No source lists them; usually in the room.
A74: 1 | B74: Year 8 | C74: Equipment and materials | D74: Grater, teaspoon, kettle and small jug (scene liquid) | F74: not stated; tools | G74: per once | I74: =IF(E74="","",IF(OR(AND(H74="Plan A",$C$5="B"),AND(H74="Plan B",$C$5="A")),0,IF(OR(G74="per student",G74="per group",G74="per class"),E74*IF(B74="Year 7",$C$3,$C$4),E74))) | L74: =IF(OR(K74="",O74<>"",I74=""),"",ROUNDUP(I74*K74,0)) | M74: Grate the soap, measure the baking soda and warm the water for the optional scene liquid (hot water is teacher-only). | N74: Optional | P74: No: tool | Q74: No source lists them; usually in the prep room.
A75: 1 | B75: Year 8 | C75: Food and consumables | D75: White coffee filters, cut into 2 cm by 10 cm strips | E75: 4 | F75: strips | G75: per once | I75: =IF(E75="","",IF(OR(AND(H75="Plan A",$C$5="B"),AND(H75="Plan B",$C$5="A")),0,IF(OR(G75="per student",G75="per group",G75="per class"),E75*IF(B75="Year 7",$C$3,$C$4),E75))) -> 4 | L75: =IF(OR(K75="",O75<>"",I75=""),"",ROUNDUP(I75*K75,0)) | M75: Chromatography strips for the pen pre-test, one per pen. | P75: Yes | Q75: Number of filters to buy is not stated; cut more if a brand has to be replaced and tested again.
A76: 1 | B76: Year 8 | C76: Food and consumables | D76: Water for the pen pre-test | F76: 1 cm deep in each of the 4 cups; water | G76: per once | I76: =IF(E76="","",IF(OR(AND(H76="Plan A",$C$5="B"),AND(H76="Plan B",$C$5="A")),0,IF(OR(G76="per student",G76="per group",G76="per class"),E76*IF(B76="Year 7",$C$3,$C$4),E76))) | L76: =IF(OR(K76="",O76<>"",I76=""),"",ROUNDUP(I76*K76,0)) | M76: Solvent for the pre-test chromatograms. | P76: No: may already exist | Q76: Tap water.
A77: 1 | B77: Year 8 | C77: Food and consumables | D77: Plain bar soap (not washing-up liquid) | E77: 1 | F77: teaspoon, grated | G77: per once | I77: =IF(E77="","",IF(OR(AND(H77="Plan A",$C$5="B"),AND(H77="Plan B",$C$5="A")),0,IF(OR(G77="per student",G77="per group",G77="per class"),E77*IF(B77="Year 7",$C$3,$C$4),E77))) -> 1 | L77: =IF(OR(K77="",O77<>"",I77=""),"",ROUNDUP(I77*K77,0)) | M77: Makes the soap solution for the optional scene liquid. | N77: Optional | P77: Yes
A78: 1 | B78: Year 8 | C78: Food and consumables | D78: Warm water for the soap solution | E78: 200 | F78: ml | G78: per once | I78: =IF(E78="","",IF(OR(AND(H78="Plan A",$C$5="B"),AND(H78="Plan B",$C$5="A")),0,IF(OR(G78="per student",G78="per group",G78="per class"),E78*IF(B78="Year 7",$C$3,$C$4),E78))) -> 200 | L78: =IF(OR(K78="",O78<>"",I78=""),"",ROUNDUP(I78*K78,0)) | M78: Dissolves the grated soap; teacher-prepared. | N78: Optional | P78: No: may already exist | Q78: Hot water is teacher-only.
A79: 1 | B79: Year 8 | C79: Food and consumables | D79: Baking soda (小苏打) | E79: 1 | F79: teaspoon | G79: per once | I79: =IF(E79="","",IF(OR(AND(H79="Plan A",$C$5="B"),AND(H79="Plan B",$C$5="A")),0,IF(OR(G79="per student",G79="per group",G79="per class"),E79*IF(B79="Year 7",$C$3,$C$4),E79))) -> 1 | L79: =IF(OR(K79="",O79<>"",I79=""),"",ROUNDUP(I79*K79,0)) | M79: Scene table copy of the white powder (evidence 3) and an ingredient of the scene liquid. | N79: Optional | P79: Yes
A80: 1 | B80: Year 8 | C80: Make beforehand | D80: Collated case files | E80: 24 | F80: case files | G80: per student | I80: =IF(E80="","",IF(OR(AND(H80="Plan A",$C$5="B"),AND(H80="Plan B",$C$5="A")),0,IF(OR(G80="per student",G80="per group",G80="per class"),E80*IF(B80="Year 7",$C$3,$C$4),E80))) -> 24 | L80: =IF(OR(K80="",O80<>"",I80=""),"",ROUNDUP(I80*K80,0)) | M80: Folder with pages in order: cover, briefing with sign-in sheet, scene map, suspect cards, evidence log; dictionary tucked inside. Used all ten weeks. | P80: Yes, see note | Q80: Not a requisition row itself; built from the folder, white card and printing rows.
A81: 1 | B81: Year 8 | C81: Make beforehand | D81: Display note (the note prop) | E81: 1 | F81: note | G81: per once | I81: =IF(E81="","",IF(OR(AND(H81="Plan A",$C$5="B"),AND(H81="Plan B",$C$5="A")),0,IF(OR(G81="per student",G81="per group",G81="per class"),E81*IF(B81="Year 7",$C$3,$C$4),E81))) -> 1 | L81: =IF(OR(K81="",O81<>"",I81=""),"",ROUNDUP(I81*K81,0)) | M81: Exact note text written with pen B on plain white card, snowflake doodle after 'Sorry!'; photographed for the Week 1 slides, on the optional scene table, held up again in the Week 3 Hook. | P81: Yes | Q81: Needs the pen pre-test done first, because pen B is chosen there.
A82: 1 | B82: Year 8 | C82: Make beforehand | D82: Pen pre-test strips (answer key) | E82: 4 | F82: strips | G82: per once | I82: =IF(E82="","",IF(OR(AND(H82="Plan A",$C$5="B"),AND(H82="Plan B",$C$5="A")),0,IF(OR(G82="per student",G82="per group",G82="per class"),E82*IF(B82="Year 7",$C$3,$C$4),E82))) -> 4 | L82: =IF(OR(K82="",O82<>"",I82=""),"",ROUNDUP(I82*K82,0)) | M82: One dried strip per pen A to D; Week 3 answer key, backup results and the strip shown in the Week 3 Hook. | P82: Yes
A83: 1 | B83: Year 8 | C83: Make beforehand | D83: Soap solution | E83: 1 | F83: small batch (about 1 teaspoon grated soap in 200 ml warm water, stirred until cloudy) | G83: per once | I83: =IF(E83="","",IF(OR(AND(H83="Plan A",$C$5="B"),AND(H83="Plan B",$C$5="A")),0,IF(OR(G83="per student",G83="per group",G83="per class"),E83*IF(B83="Year 7",$C$3,$C$4),E83))) -> 1 | L83: =IF(OR(K83="",O83<>"",I83=""),"",ROUNDUP(I83*K83,0)) | M83: Half of the optional scene liquid. | N83: Optional | P83: Yes
A84: 1 | B84: Year 8 | C84: Make beforehand | D84: Baking soda solution | E84: 1 | F84: small batch | G84: per once | I84: =IF(E84="","",IF(OR(AND(H84="Plan A",$C$5="B"),AND(H84="Plan B",$C$5="A")),0,IF(OR(G84="per student",G84="per group",G84="per class"),E84*IF(B84="Year 7",$C$3,$C$4),E84))) -> 1 | L84: =IF(OR(K84="",O84<>"",I84=""),"",ROUNDUP(I84*K84,0)) | M84: Other half of the optional scene liquid. | N84: Optional | P84: Yes, see note | Q84: Recipe not in the sources; the requisition's 'a pinch of baking soda in a little water' needs confirming.
A85: 1 | B85: Year 8 | C85: Make beforehand | D85: Evidence 4: scene liquid | E85: 1 | F85: saucer | G85: per class | I85: =IF(E85="","",IF(OR(AND(H85="Plan A",$C$5="B"),AND(H85="Plan B",$C$5="A")),0,IF(OR(G85="per student",G85="per group",G85="per class"),E85*IF(B85="Year 7",$C$3,$C$4),E85))) -> 1 | L85: =IF(OR(K85="",O85<>"",I85=""),"",ROUNDUP(I85*K85,0)) | M85: Scene table copy of the puddle: soap solution and baking soda solution mixed in equal amounts. | N85: Optional | P85: Yes | Q85: Amount for the saucer not stated; a little is enough.
A86: 1 | B86: Year 8 | C86: Make beforehand | D86: Scene table display | E86: 1 | F86: display | G86: per class | I86: =IF(E86="","",IF(OR(AND(H86="Plan A",$C$5="B"),AND(H86="Plan B",$C$5="A")),0,IF(OR(G86="per student",G86="per group",G86="per class"),E86*IF(B86="Year 7",$C$3,$C$4),E86))) -> 1 | L86: =IF(OR(K86="",O86<>"",I86=""),"",ROUNDUP(I86*K86,0)) | M86: Glass, pen-B note, teaspoon of baking soda on a dark tray, saucer of scene liquid, 24 cm paper footprint and the do-not-touch sign at the front; look only. | N86: Optional | P86: Yes
A87: 2 | B87: Year 7 | C87: Printing (paper copies) | D87: Worksheet: Thought experiments (Do Now box, Core, Stretch, Challenge, My thinking, fold-under word bank, exit ticket strip) | E87: 24 | F87: copies; 4 A4 pages, double-sided (2 sheets per copy, 48 sheets) | G87: per student | I87: =IF(E87="","",IF(OR(AND(H87="Plan A",$C$5="B"),AND(H87="Plan B",$C$5="A")),0,IF(OR(G87="per student",G87="per group",G87="per class"),E87*IF(B87="Year 7",$C$3,$C$4),E87))) -> 24 | J87: A4 paper | K87: 2 | L87: =IF(OR(K87="",O87<>"",I87=""),"",ROUNDUP(I87*K87,0)) -> 48 | M87: Main student task for the whole lesson; the exit ticket strip is at the foot of page 4 | P87: No: paper printing | Q87: No spares stated (kit card: 1 per student). Pages 1 to 3 end 'turn over 请翻页', which points to double-sided printing; if so, cutting off the exit ticket strip at the foot of page 4 also cuts away the foot of page 3 (Challenge A writing lines). Print only from the Year 7 design rebuilt after the language pass (Teacher Guide prep calendar).
A88: 2 | B88: Year 7 | C88: Printing (paper copies) | D88: Galileo thought-experiment storyboard poster | E88: 1 | F88: copy; A3 landscape, single-sided | G88: per class | I88: =IF(E88="","",IF(OR(AND(H88="Plan A",$C$5="B"),AND(H88="Plan B",$C$5="A")),0,IF(OR(G88="per student",G88="per group",G88="per class"),E88*IF(B88="Year 7",$C$3,$C$4),E88))) -> 1 | J88: A3 paper | K88: 1 | L88: =IF(OR(K88="",O88<>"",I88=""),"",ROUNDUP(I88*K88,0)) -> 1 | M88: Learn phase: the six-panel Galileo storyboard (also shown on Slide 5); supports Core A | P88: Yes | Q88: Print spec: 1 per class. One poster can stay up for every class taught in the same room.
A89: 2 | B89: Year 7 | C89: Printing (paper copies) | D89: Galileo storyboard, A4 table copies | E89: 6 | F89: copies; A4 landscape, single-sided | G89: per group | I89: =IF(E89="","",IF(OR(AND(H89="Plan A",$C$5="B"),AND(H89="Plan B",$C$5="A")),0,IF(OR(G89="per student",G89="per group",G89="per class"),E89*IF(B89="Year 7",$C$3,$C$4),E89))) -> 6 | J89: A4 paper | K89: 1 | L89: =IF(OR(K89="",O89<>"",I89=""),"",ROUNDUP(I89*K89,0)) -> 6 | M89: One per group table, to support Core A (putting the storyboard captions in order) | N89: Optional | P89: No: paper printing | Q89: The print spec says 'if wanted'. Scaled down from the A3 design, so check the Chinese gist lines are still readable.
A90: 2 | B90: Year 7 | C90: Printing (paper copies) | D90: Kit card (half-A4, marked Teacher copy, includes the key to the cup contents) | E90: 1 | F90: copy; A5 landscape, single-sided | G90: per class | I90: =IF(E90="","",IF(OR(AND(H90="Plan A",$C$5="B"),AND(H90="Plan B",$C$5="A")),0,IF(OR(G90="per student",G90="per group",G90="per class"),E90*IF(B90="Year 7",$C$3,$C$4),E90))) -> 1 | J90: A5 paper | K90: 1 | L90: =IF(OR(K90="",O90<>"",I90=""),"",ROUNDUP(I90*K90,0)) -> 1 | M90: Teacher kit list, prep steps, hazards and clean-up; teacher key to mystery cups A to L | P90: No: paper printing | Q90: The card carries the cup key, which must stay on the teacher desk, so do not put it on the group tables for the Safety Officer.
A91: 2 | B91: Year 7 | C91: Card, laminating and stationery | D91: Question sort cards (12 question cards + 2 header cards: Testable, Not testable) | E91: 6 | F91: sets; 2 A4 sheets of card per set (sheet 1: 10 cards, sheet 2: 2 question cards + 2 header cards), single-sided, business-card size (8.5 cm x 5.5 cm) | G91: per group | I91: =IF(E91="","",IF(OR(AND(H91="Plan A",$C$5="B"),AND(H91="Plan B",$C$5="A")),0,IF(OR(G91="per student",G91="per group",G91="per class"),E91*IF(B91="Year 7",$C$3,$C$4),E91))) -> 6 | J91: A4 card | K91: 2 | L91: =IF(OR(K91="",O91<>"",I91=""),"",ROUNDUP(I91*K91,0)) -> 12 | M91: Do phase card sort: testable or not testable (about 8 minutes) | P91: Yes | Q91: 6 sets x 2 sheets = 12 sheets of A4 white card, matching the requisition. Spec says 'on card if possible'. Cards are counted back into envelopes at clean-up, so one set of 6 could serve every class.
A92: 2 | B92: Year 7 | C92: Card, laminating and stationery | D92: Envelopes, small, for the sort card sets | E92: 6 | F92: envelopes | G92: per group | I92: =IF(E92="","",IF(OR(AND(H92="Plan A",$C$5="B"),AND(H92="Plan B",$C$5="A")),0,IF(OR(G92="per student",G92="per group",G92="per class"),E92*IF(B92="Year 7",$C$3,$C$4),E92))) -> 6 | L92: =IF(OR(K92="",O92<>"",I92=""),"",ROUNDUP(I92*K92,0)) | M92: One envelope per group holding a set of 12 question cards and 2 header cards | P92: Yes
A93: 2 | B93: Year 7 | C93: Card, laminating and stationery | D93: Masking tape | E93: 1 | F93: roll | G93: per once | I93: =IF(E93="","",IF(OR(AND(H93="Plan A",$C$5="B"),AND(H93="Plan B",$C$5="A")),0,IF(OR(G93="per student",G93="per group",G93="per class"),E93*IF(B93="Year 7",$C$3,$C$4),E93))) -> 1 | L93: =IF(OR(K93="",O93<>"",I93=""),"",ROUNDUP(I93*K93,0)) | M93: Taping each pair of cups rim to rim to seal the 12 mystery cups; re-taping any loose cup | P93: Yes | Q93: The kit card names masking tape but no amount; 1 roll is the requisition figure.
A94: 2 | B94: Year 7 | C94: Card, laminating and stationery | D94: Marker pen | E94: 1 | F94: pen | G94: per once | I94: =IF(E94="","",IF(OR(AND(H94="Plan A",$C$5="B"),AND(H94="Plan B",$C$5="A")),0,IF(OR(G94="per student",G94="per group",G94="per class"),E94*IF(B94="Year 7",$C$3,$C$4),E94))) -> 1 | L94: =IF(OR(K94="",O94<>"",I94=""),"",ROUNDUP(I94*K94,0)) | M94: Labelling the mystery cups A to L underneath | P94: Yes | Q94: The kit card says 'label A to L underneath' but does not name a pen; any permanent marker will do.
A95: 2 | B95: Year 7 | C95: Card, laminating and stationery | D95: Pencils | E95: 24 | F95: pencils | G95: per student | I95: =IF(E95="","",IF(OR(AND(H95="Plan A",$C$5="B"),AND(H95="Plan B",$C$5="A")),0,IF(OR(G95="per student",G95="per group",G95="per class"),E95*IF(B95="Year 7",$C$3,$C$4),E95))) -> 24 | L95: =IF(OR(K95="",O95<>"",I95=""),"",ROUNDUP(I95*K95,0)) | M95: Writing on the worksheet, exit ticket and logbook (kit card: 1 per student) | O95: Bought for Week 1; reuse | P95: Yes, see note | Q95: The Week 2 requisition lists 24 pencils again although they were bought for Week 1; no new order needed.
A96: 2 | B96: Year 7 | C96: Card, laminating and stationery | D96: Scientist's Logbook (A5 booklet) | E96: 24 | F96: booklets | G96: per student | I96: =IF(E96="","",IF(OR(AND(H96="Plan A",$C$5="B"),AND(H96="Plan B",$C$5="A")),0,IF(OR(G96="per student",G96="per group",G96="per class"),E96*IF(B96="Year 7",$C$3,$C$4),E96))) -> 24 | L96: =IF(OR(K96="",O96<>"",I96=""),"",ROUNDUP(I96*K96,0)) | M96: Logbook line in Think and Reflect ('What I found') | O96: Started in Week 1; kept in the class box | P96: Yes, see note | Q96: The Week 2 requisition lists 24 logbooks again ('Same booklets'); they are the Week 1 booklets, so no new order is needed.
A97: 2 | B97: Year 7 | C97: Card, laminating and stationery | D97: Group role cards with duties (6 cards per set incl. Language buddy card, laminated) | E97: 6 | F97: sets | G97: per group | I97: =IF(E97="","",IF(OR(AND(H97="Plan A",$C$5="B"),AND(H97="Plan B",$C$5="A")),0,IF(OR(G97="per student",G97="per group",G97="per class"),E97*IF(B97="Year 7",$C$3,$C$4),E97))) -> 6 | L97: =IF(OR(K97="",O97<>"",I97=""),"",ROUNDUP(I97*K97,0)) | M97: Roles for the card sort: Lead Scientist reads, Recorder sorts, Reporter explains; language buddy reads the Chinese on each card | O97: Printed and laminated for Week 1; reuse | P97: No: reused | Q97: Roles rotate weekly.
A98: 2 | B98: Year 7 | C98: Card, laminating and stationery | D98: Sentence frame card sets, Year 7 Ice Engineers (A6 cards, one frame per card) | E98: 6 | F98: sets | G98: per group | I98: =IF(E98="","",IF(OR(AND(H98="Plan A",$C$5="B"),AND(H98="Plan B",$C$5="A")),0,IF(OR(G98="per student",G98="per group",G98="per class"),E98*IF(B98="Year 7",$C$3,$C$4),E98))) -> 6 | L98: =IF(OR(K98="",O98<>"",I98=""),"",ROUNDUP(I98*K98,0)) | M98: Frames on group tables; Week 2 frames: 'I predict ___ because ___.' and 'If ___, then ___.' | O98: Due to be printed with the language support pack before Week 1 (Teacher Guide prep calendar); reuse | P98: No: may already exist | Q98: Not in the Week 1 or Week 2 requisition. If not yet printed: 6 sets of 16 cards, 4 per A4 sheet = 4 sheets per set, 24 A4 sheets.
A99: 2 | B99: Year 7 | C99: Card, laminating and stationery | D99: Classroom language card (A5, two-sided, laminated) | E99: 24 | F99: cards | G99: per student | I99: =IF(E99="","",IF(OR(AND(H99="Plan A",$C$5="B"),AND(H99="Plan B",$C$5="A")),0,IF(OR(G99="per student",G99="per group",G99="per class"),E99*IF(B99="Year 7",$C$3,$C$4),E99))) -> 24 | L99: =IF(OR(K99="",O99<>"",I99=""),"",ROUNDUP(I99*K99,0)) | M99: Help phrases; the Teacher Guide repeats the two-minute walk-through (with the Instruction words key) in the two Do Nows after the first | O99: Laminated for Week 1 (30 printed: 24 + 6 spares); reuse | P99: No: reused | Q99: The Week 2 Do Now (4 minutes) is already full with the mystery cups and the Today slide; decide whether the walk-through repeat fits.
A100: 2 | B100: Year 7 | C100: Card, laminating and stationery | D100: My Science Dictionary, Year 7 (A5 booklet) | E100: 24 | F100: booklets | G100: per student | I100: =IF(E100="","",IF(OR(AND(H100="Plan A",$C$5="B"),AND(H100="Plan B",$C$5="A")),0,IF(OR(G100="per student",G100="per group",G100="per class"),E100*IF(B100="Year 7",$C$3,$C$4),E100))) -> 24 | L100: =IF(OR(K100="",O100<>"",I100=""),"",ROUNDUP(I100*K100,0)) | M100: Key word meanings in English and Chinese; open in every lesson | O100: Given out in Week 1 (28 printed: 24 + 4 spares); reuse | P100: No: reused | Q100: Not named in the Week 2 lesson file; the Teacher Guide says the dictionary is open in every lesson.
A101: 2 | B101: Year 7 | C101: Equipment and materials | D101: Class box | E101: 1 | F101: box | G101: per class | I101: =IF(E101="","",IF(OR(AND(H101="Plan A",$C$5="B"),AND(H101="Plan B",$C$5="A")),0,IF(OR(G101="per student",G101="per group",G101="per class"),E101*IF(B101="Year 7",$C$3,$C$4),E101))) -> 1 | L101: =IF(OR(K101="",O101<>"",I101=""),"",ROUNDUP(I101*K101,0)) | M101: Storing logbooks, collected at the end of the lesson | O101: Week 1 class box; reuse | P101: No: reused
...

Sheet Prep by week
A1: Prep by week: how much time each lesson takes to get ready
A2: Minutes come from the kit cards where they give them; the rest are estimates (marked). "After" is marking, the tracker and putting kit away. "Could be done by someone else" means a technician, assistant, reprographics or the students. Uses the classes and freezer plan on the All weeks sheet: until a Year 7 freezer plan is chosen, Weeks 5 to 8 count the prep for both plans.
A4: Week | B4: Year 7: before the lesson (min) | C4: Year 7: after (marking, admin) | D4: Year 7: could be done by someone else | E4: Year 8: before the lesson (min) | F4: Year 8: after (marking, admin) | G4: Year 8: could be done by someone else | H4: Both years, before and after (hours) | I4: Optional extras (min, not counted)
A5: 1 | B5: =SUMIFS($L$19:$L$380,$A$19:$A$380,$A5,$B$19:$B$380,"Year 7",$J$19:$J$380,"No",$C$19:$C$380,"<>After the lesson") -> 187 | C5: =SUMIFS($L$19:$L$380,$A$19:$A$380,$A5,$B$19:$B$380,"Year 7",$J$19:$J$380,"No",$C$19:$C$380,"After the lesson") -> 108 | D5: =SUMIFS($L$19:$L$380,$A$19:$A$380,$A5,$B$19:$B$380,"Year 7",$J$19:$J$380,"No",$G$19:$G$380,"<>Teacher") -> 182 | E5: =SUMIFS($L$19:$L$380,$A$19:$A$380,$A5,$B$19:$B$380,"Year 8",$J$19:$J$380,"No",$C$19:$C$380,"<>After the lesson") -> 220 | F5: =SUMIFS($L$19:$L$380,$A$19:$A$380,$A5,$B$19:$B$380,"Year 8",$J$19:$J$380,"No",$C$19:$C$380,"After the lesson") -> 105 | G5: =SUMIFS($L$19:$L$380,$A$19:$A$380,$A5,$B$19:$B$380,"Year 8",$J$19:$J$380,"No",$G$19:$G$380,"<>Teacher") -> 155 | H5: =ROUND((B5+C5+E5+F5)/60,1) -> 10.3 | I5: =SUMIFS($L$19:$L$380,$A$19:$A$380,$A5,$J$19:$J$380,"Optional") -> 60
A6: 2 | B6: =SUMIFS($L$19:$L$380,$A$19:$A$380,$A6,$B$19:$B$380,"Year 7",$J$19:$J$380,"No",$C$19:$C$380,"<>After the lesson") -> 67 | C6: =SUMIFS($L$19:$L$380,$A$19:$A$380,$A6,$B$19:$B$380,"Year 7",$J$19:$J$380,"No",$C$19:$C$380,"After the lesson") -> 26 | D6: =SUMIFS($L$19:$L$380,$A$19:$A$380,$A6,$B$19:$B$380,"Year 7",$J$19:$J$380,"No",$G$19:$G$380,"<>Teacher") -> 63 | E6: =SUMIFS($L$19:$L$380,$A$19:$A$380,$A6,$B$19:$B$380,"Year 8",$J$19:$J$380,"No",$C$19:$C$380,"<>After the lesson") -> 50 | F6: =SUMIFS($L$19:$L$380,$A$19:$A$380,$A6,$B$19:$B$380,"Year 8",$J$19:$J$380,"No",$C$19:$C$380,"After the lesson") -> 21 | G6: =SUMIFS($L$19:$L$380,$A$19:$A$380,$A6,$B$19:$B$380,"Year 8",$J$19:$J$380,"No",$G$19:$G$380,"<>Teacher") -> 46 | H6: =ROUND((B6+C6+E6+F6)/60,1) -> 2.7 | I6: =SUMIFS($L$19:$L$380,$A$19:$A$380,$A6,$J$19:$J$380,"Optional") -> 7
A7: 3 | B7: =SUMIFS($L$19:$L$380,$A$19:$A$380,$A7,$B$19:$B$380,"Year 7",$J$19:$J$380,"No",$C$19:$C$380,"<>After the lesson") -> 57 | C7: =SUMIFS($L$19:$L$380,$A$19:$A$380,$A7,$B$19:$B$380,"Year 7",$J$19:$J$380,"No",$C$19:$C$380,"After the lesson") -> 20 | D7: =SUMIFS($L$19:$L$380,$A$19:$A$380,$A7,$B$19:$B$380,"Year 7",$J$19:$J$380,"No",$G$19:$G$380,"<>Teacher") -> 50 | E7: =SUMIFS($L$19:$L$380,$A$19:$A$380,$A7,$B$19:$B$380,"Year 8",$J$19:$J$380,"No",$C$19:$C$380,"<>After the lesson") -> 82 | F7: =SUMIFS($L$19:$L$380,$A$19:$A$380,$A7,$B$19:$B$380,"Year 8",$J$19:$J$380,"No",$C$19:$C$380,"After the lesson") -> 23 | G7: =SUMIFS($L$19:$L$380,$A$19:$A$380,$A7,$B$19:$B$380,"Year 8",$J$19:$J$380,"No",$G$19:$G$380,"<>Teacher") -> 73 | H7: =ROUND((B7+C7+E7+F7)/60,1) -> 3 | I7: =SUMIFS($L$19:$L$380,$A$19:$A$380,$A7,$J$19:$J$380,"Optional") -> 10
A8: 4 | B8: =SUMIFS($L$19:$L$380,$A$19:$A$380,$A8,$B$19:$B$380,"Year 7",$J$19:$J$380,"No",$C$19:$C$380,"<>After the lesson") -> 40 | C8: =SUMIFS($L$19:$L$380,$A$19:$A$380,$A8,$B$19:$B$380,"Year 7",$J$19:$J$380,"No",$C$19:$C$380,"After the lesson") -> 18 | D8: =SUMIFS($L$19:$L$380,$A$19:$A$380,$A8,$B$19:$B$380,"Year 7",$J$19:$J$380,"No",$G$19:$G$380,"<>Teacher") -> 31 | E8: =SUMIFS($L$19:$L$380,$A$19:$A$380,$A8,$B$19:$B$380,"Year 8",$J$19:$J$380,"No",$C$19:$C$380,"<>After the lesson") -> 70 | F8: =SUMIFS($L$19:$L$380,$A$19:$A$380,$A8,$B$19:$B$380,"Year 8",$J$19:$J$380,"No",$C$19:$C$380,"After the lesson") -> 34 | G8: =SUMIFS($L$19:$L$380,$A$19:$A$380,$A8,$B$19:$B$380,"Year 8",$J$19:$J$380,"No",$G$19:$G$380,"<>Teacher") -> 54 | H8: =ROUND((B8+C8+E8+F8)/60,1) -> 2.7 | I8: =SUMIFS($L$19:$L$380,$A$19:$A$380,$A8,$J$19:$J$380,"Optional") -> 7
A9: 5 | B9: =SUMIFS($L$19:$L$380,$A$19:$A$380,$A9,$B$19:$B$380,"Year 7",$J$19:$J$380,"No",$C$19:$C$380,"<>After the lesson") -> 40 | C9: =SUMIFS($L$19:$L$380,$A$19:$A$380,$A9,$B$19:$B$380,"Year 7",$J$19:$J$380,"No",$C$19:$C$380,"After the lesson") -> 144 | D9: =SUMIFS($L$19:$L$380,$A$19:$A$380,$A9,$B$19:$B$380,"Year 7",$J$19:$J$380,"No",$G$19:$G$380,"<>Teacher") -> 60 | E9: =SUMIFS($L$19:$L$380,$A$19:$A$380,$A9,$B$19:$B$380,"Year 8",$J$19:$J$380,"No",$C$19:$C$380,"<>After the lesson") -> 84 | F9: =SUMIFS($L$19:$L$380,$A$19:$A$380,$A9,$B$19:$B$380,"Year 8",$J$19:$J$380,"No",$C$19:$C$380,"After the lesson") -> 75 | G9: =SUMIFS($L$19:$L$380,$A$19:$A$380,$A9,$B$19:$B$380,"Year 8",$J$19:$J$380,"No",$G$19:$G$380,"<>Teacher") -> 43 | H9: =ROUND((B9+C9+E9+F9)/60,1) -> 5.7 | I9: =SUMIFS($L$19:$L$380,$A$19:$A$380,$A9,$J$19:$J$380,"Optional") -> 15
A10: 6 | B10: =SUMIFS($L$19:$L$380,$A$19:$A$380,$A10,$B$19:$B$380,"Year 7",$J$19:$J$380,"No",$C$19:$C$380,"<>After the lesson") -> 110 | C10: =SUMIFS($L$19:$L$380,$A$19:$A$380,$A10,$B$19:$B$380,"Year 7",$J$19:$J$380,"No",$C$19:$C$380,"After the lesson") -> 33 | D10: =SUMIFS($L$19:$L$380,$A$19:$A$380,$A10,$B$19:$B$380,"Year 7",$J$19:$J$380,"No",$G$19:$G$380,"<>Teacher") -> 101 | E10: =SUMIFS($L$19:$L$380,$A$19:$A$380,$A10,$B$19:$B$380,"Year 8",$J$19:$J$380,"No",$C$19:$C$380,"<>After the lesson") -> 103 | F10: =SUMIFS($L$19:$L$380,$A$19:$A$380,$A10,$B$19:$B$380,"Year 8",$J$19:$J$380,"No",$C$19:$C$380,"After the lesson") -> 28 | G10: =SUMIFS($L$19:$L$380,$A$19:$A$380,$A10,$B$19:$B$380,"Year 8",$J$19:$J$380,"No",$G$19:$G$380,"<>Teacher") -> 56 | H10: =ROUND((B10+C10+E10+F10)/60,1) -> 4.6 | I10: =SUMIFS($L$19:$L$380,$A$19:$A$380,$A10,$J$19:$J$380,"Optional") -> 10
A11: 7 | B11: =SUMIFS($L$19:$L$380,$A$19:$A$380,$A11,$B$19:$B$380,"Year 7",$J$19:$J$380,"No",$C$19:$C$380,"<>After the lesson") -> 170 | C11: =SUMIFS($L$19:$L$380,$A$19:$A$380,$A11,$B$19:$B$380,"Year 7",$J$19:$J$380,"No",$C$19:$C$380,"After the lesson") -> 40 | D11: =SUMIFS($L$19:$L$380,$A$19:$A$380,$A11,$B$19:$B$380,"Year 7",$J$19:$J$380,"No",$G$19:$G$380,"<>Teacher") -> 147 | E11: =SUMIFS($L$19:$L$380,$A$19:$A$380,$A11,$B$19:$B$380,"Year 8",$J$19:$J$380,"No",$C$19:$C$380,"<>After the lesson") -> 50 | F11: =SUMIFS($L$19:$L$380,$A$19:$A$380,$A11,$B$19:$B$380,"Year 8",$J$19:$J$380,"No",$C$19:$C$380,"After the lesson") -> 43 | G11: =SUMIFS($L$19:$L$380,$A$19:$A$380,$A11,$B$19:$B$380,"Year 8",$J$19:$J$380,"No",$G$19:$G$380,"<>Teacher") -> 13 | H11: =ROUND((B11+C11+E11+F11)/60,1) -> 5.1 | I11: =SUMIFS($L$19:$L$380,$A$19:$A$380,$A11,$J$19:$J$380,"Optional") -> 60
A12: 8 | B12: =SUMIFS($L$19:$L$380,$A$19:$A$380,$A12,$B$19:$B$380,"Year 7",$J$19:$J$380,"No",$C$19:$C$380,"<>After the lesson") -> 146 | C12: =SUMIFS($L$19:$L$380,$A$19:$A$380,$A12,$B$19:$B$380,"Year 7",$J$19:$J$380,"No",$C$19:$C$380,"After the lesson") -> 27 | D12: =SUMIFS($L$19:$L$380,$A$19:$A$380,$A12,$B$19:$B$380,"Year 7",$J$19:$J$380,"No",$G$19:$G$380,"<>Teacher") -> 130 | E12: =SUMIFS($L$19:$L$380,$A$19:$A$380,$A12,$B$19:$B$380,"Year 8",$J$19:$J$380,"No",$C$19:$C$380,"<>After the lesson") -> 205 | F12: =SUMIFS($L$19:$L$380,$A$19:$A$380,$A12,$B$19:$B$380,"Year 8",$J$19:$J$380,"No",$C$19:$C$380,"After the lesson") -> 78 | G12: =SUMIFS($L$19:$L$380,$A$19:$A$380,$A12,$B$19:$B$380,"Year 8",$J$19:$J$380,"No",$G$19:$G$380,"<>Teacher") -> 148 | H12: =ROUND((B12+C12+E12+F12)/60,1) -> 7.6 | I12: =SUMIFS($L$19:$L$380,$A$19:$A$380,$A12,$J$19:$J$380,"Optional") -> 30
A13: 9 | B13: =SUMIFS($L$19:$L$380,$A$19:$A$380,$A13,$B$19:$B$380,"Year 7",$J$19:$J$380,"No",$C$19:$C$380,"<>After the lesson") -> 75 | C13: =SUMIFS($L$19:$L$380,$A$19:$A$380,$A13,$B$19:$B$380,"Year 7",$J$19:$J$380,"No",$C$19:$C$380,"After the lesson") -> 51 | D13: =SUMIFS($L$19:$L$380,$A$19:$A$380,$A13,$B$19:$B$380,"Year 7",$J$19:$J$380,"No",$G$19:$G$380,"<>Teacher") -> 48 | E13: =SUMIFS($L$19:$L$380,$A$19:$A$380,$A13,$B$19:$B$380,"Year 8",$J$19:$J$380,"No",$C$19:$C$380,"<>After the lesson") -> 68 | F13: =SUMIFS($L$19:$L$380,$A$19:$A$380,$A13,$B$19:$B$380,"Year 8",$J$19:$J$380,"No",$C$19:$C$380,"After the lesson") -> 108 | G13: =SUMIFS($L$19:$L$380,$A$19:$A$380,$A13,$B$19:$B$380,"Year 8",$J$19:$J$380,"No",$G$19:$G$380,"<>Teacher") -> 36 | H13: =ROUND((B13+C13+E13+F13)/60,1) -> 5 | I13: =SUMIFS($L$19:$L$380,$A$19:$A$380,$A13,$J$19:$J$380,"Optional") -> 18
A14: 10 | B14: =SUMIFS($L$19:$L$380,$A$19:$A$380,$A14,$B$19:$B$380,"Year 7",$J$19:$J$380,"No",$C$19:$C$380,"<>After the lesson") -> 66 | C14: =SUMIFS($L$19:$L$380,$A$19:$A$380,$A14,$B$19:$B$380,"Year 7",$J$19:$J$380,"No",$C$19:$C$380,"After the lesson") -> 315 | D14: =SUMIFS($L$19:$L$380,$A$19:$A$380,$A14,$B$19:$B$380,"Year 7",$J$19:$J$380,"No",$G$19:$G$380,"<>Teacher") -> 81 | E14: =SUMIFS($L$19:$L$380,$A$19:$A$380,$A14,$B$19:$B$380,"Year 8",$J$19:$J$380,"No",$C$19:$C$380,"<>After the lesson") -> 62 | F14: =SUMIFS($L$19:$L$380,$A$19:$A$380,$A14,$B$19:$B$380,"Year 8",$J$19:$J$380,"No",$C$19:$C$380,"After the lesson") -> 333 | G14: =SUMIFS($L$19:$L$380,$A$19:$A$380,$A14,$B$19:$B$380,"Year 8",$J$19:$J$380,"No",$G$19:$G$380,"<>Teacher") -> 41 | H14: =ROUND((B14+C14+E14+F14)/60,1) -> 12.9 | I14: =SUMIFS($L$19:$L$380,$A$19:$A$380,$A14,$J$19:$J$380,"Optional") -> 63
A15: Total | B15: =SUM(B5:B14) -> 958 | C15: =SUM(C5:C14) -> 782 | D15: =SUM(D5:D14) -> 893 | E15: =SUM(E5:E14) -> 994 | F15: =SUM(F5:F14) -> 848 | G15: =SUM(G5:G14) -> 665 | H15: =SUM(H5:H14) -> 59.6 | I15: =SUM(I5:I14) -> 280
A17: All prep tasks
A18: Week | B18: Year | C18: When | D18: Task | E18: Minutes (one class) | F18: Minutes from | G18: Who could do it | H18: Once for all classes? | I18: Reused later | J18: Optional? | K18: Plan | L18: Minutes for your classes
A19: 1 | B19: Year 7 | C19: 2 or more weeks before | D19: Order the Week 1 kit from the requisition: A4 card, A4 (C4) envelopes, A4 and A5 laminating pouches, A3 paper, name cards, HB pencils and the class box. | E19: 15 | F19: estimate | G19: Technician or assistant | H19: Yes | J19: No | L19: =IF(E19="","",IF(OR(AND(K19="Plan A",'All weeks'!$C$5="B"),AND(K19="Plan B",'All weeks'!$C$5="A")),0,IF(H19="Yes",E19,E19*IF(B19="Year 7",'All weeks'!$C$3,'All weeks'!$C$4)))) -> 15
A20: 1 | B20: Year 7 | C20: 2 or more weeks before | D20: Send the booklet jobs to reprographics: Scientist's Logbook (24 per class) and My Science Dictionary (28 per class, A5 saddle-stitched, 24 or 28 pages, 90 gsm). | E20: 10 | F20: estimate | G20: Teacher | H20: Yes | I20: Weeks 2 to 10 | J20: No | L20: =IF(E20="","",IF(OR(AND(K20="Plan A",'All weeks'!$C$5="B"),AND(K20="Plan B",'All weeks'!$C$5="A")),0,IF(H20="Yes",E20,E20*IF(B20="Year 7",'All weeks'!$C$3,'All weeks'!$C$4)))) -> 10
A21: 1 | B21: Year 7 | C21: The week before | D21: Print the group role cards (6 A4 sheets), laminate them (6 A4 pouches), cut into 36 cards and sort into 6 sets of 6. | E21: 25 | F21: estimate | G21: Technician or assistant | H21: No | I21: Weeks 2 to 10 | J21: No | L21: =IF(E21="","",IF(OR(AND(K21="Plan A",'All weeks'!$C$5="B"),AND(K21="Plan B",'All weeks'!$C$5="A")),0,IF(H21="Yes",E21,E21*IF(B21="Year 7",'All weeks'!$C$3,'All weeks'!$C$4)))) -> 25
A22: 1 | B22: Year 7 | C22: The week before | D22: Print the classroom language cards double-sided (30 A5, or 15 A4 sheets cut in half) and laminate them (30 A5 pouches). | E22: 30 | F22: estimate | G22: Technician or assistant | H22: No | I22: Weeks 2 to 10 | J22: No | L22: =IF(E22="","",IF(OR(AND(K22="Plan A",'All weeks'!$C$5="B"),AND(K22="Plan B",'All weeks'!$C$5="A")),0,IF(H22="Yes",E22,E22*IF(B22="Year 7",'All weeks'!$C$3,'All weeks'!$C$4)))) -> 30
A23: 1 | B23: Year 7 | C23: The week before | D23: Print the footprint puzzle cards on A4 card: 6 sets of Stage 1, 2 and 3 (18 sheets), with the teacher note on the back of each Card 3. | E23: 10 | F23: estimate | G23: Technician or assistant | H23: No | J23: No | L23: =IF(E23="","",IF(OR(AND(K23="Plan A",'All weeks'!$C$5="B"),AND(K23="Plan B",'All weeks'!$C$5="A")),0,IF(H23="Yes",E23,E23*IF(B23="Year 7",'All weeks'!$C$3,'All weeks'!$C$4)))) -> 10
A24: 1 | B24: Year 7 | C24: The week before | D24: Only if not using card: print the 18 puzzle cards on paper and laminate them (18 A4 pouches). | E24: 20 | F24: estimate | G24: Technician or assistant | H24: No | J24: Optional | L24: =IF(E24="","",IF(OR(AND(K24="Plan A",'All weeks'!$C$5="B"),AND(K24="Plan B",'All weeks'!$C$5="A")),0,IF(H24="Yes",E24,E24*IF(B24="Year 7",'All weeks'!$C$3,'All weeks'!$C$4)))) -> 20
A25: 1 | B25: Year 7 | C25: The week before | D25: Print the worksheets: 24 copies, 4 pages double-sided (48 sheets), from the design rebuilt after the language pass (discard any earlier copies). First check the exit ticket cut line against the My thinking box on the back. | E25: 5 | F25: estimate | G25: Reprographics | H25: No | J25: No | L25: =IF(E25="","",IF(OR(AND(K25="Plan A",'All weeks'!$C$5="B"),AND(K25="Plan B",'All weeks'!$C$5="A")),0,IF(H25="Yes",E25,E25*IF(B25="Year 7",'All weeks'!$C$3,'All weeks'!$C$4)))) -> 5
A26: 1 | B26: Year 7 | C26: The week before | D26: Print and sort the skills check papers (3 sheets each, double-sided) and survey papers (2 per A4, cut in half) in class order. | E26: 10 | F26: kit card | G26: Technician or assistant | H26: No | J26: No | L26: =IF(E26="","",IF(OR(AND(K26="Plan A",'All weeks'!$C$5="B"),AND(K26="Plan B",'All weeks'!$C$5="A")),0,IF(H26="Yes",E26,E26*IF(B26="Year 7",'All weeks'!$C$3,'All weeks'!$C$4)))) -> 10
A27: 1 | B27: Year 7 | C27: The week before | D27: Print the teacher copies: skills check mark scheme (2 pages) and the Week 1 kit card. | E27: 3 | F27: estimate | G27: Teacher | H27: Yes | J27: No | L27: =IF(E27="","",IF(OR(AND(K27="Plan A",'All weeks'!$C$5="B"),AND(K27="Plan B",'All weeks'!$C$5="A")),0,IF(H27="Yes",E27,E27*IF(B27="Year 7",'All weeks'!$C$3,'All weeks'!$C$4)))) -> 3
A28: 1 | B28: Year 7 | C28: The week before | D28: Print the three A3 posters (Instruction words, Classroom language side B, Think in any language) and the A4 sentence frame poster; put them up on the wall. | E28: 15 | F28: estimate | G28: Technician or assistant | H28: Yes | I28: Weeks 2 to 10 | J28: No | L28: =IF(E28="","",IF(OR(AND(K28="Plan A",'All weeks'!$C$5="B"),AND(K28="Plan B",'All weeks'!$C$5="A")),0,IF(H28="Yes",E28,E28*IF(B28="Year 7",'All weeks'!$C$3,'All weeks'!$C$4)))) -> 15
A29: 1 | B29: Year 7 | C29: The week before | D29: Print and cut the sentence frame bank cards: 24 A4 sheets into 6 sets of 16 A6 cards. | E29: 20 | F29: estimate | G29: Technician or assistant | H29: No | I29: Weeks 2 to 10 | J29: No | L29: =IF(E29="","",IF(OR(AND(K29="Plan A",'All weeks'!$C$5="B"),AND(K29="Plan B",'All weeks'!$C$5="A")),0,IF(H29="Yes",E29,E29*IF(B29="Year 7",'All weeks'!$C$3,'All weeks'!$C$4)))) -> 20
A30: 1 | B30: Year 7 | C30: The week before | D30: Write the group seating plan: six groups of 3 or 4, each Band 1 student beside a Band 3 language buddy, with a starting role for each student. | E30: 10 | F30: estimate | G30: Teacher | H30: No | I30: Weeks 2 to 5 | J30: No | L30: =IF(E30="","",IF(OR(AND(K30="Plan A",'All weeks'!$C$5="B"),AND(K30="Plan B",'All weeks'!$C$5="A")),0,IF(H30="Yes",E30,E30*IF(B30="Year 7",'All weeks'!$C$3,'All weeks'!$C$4)))) -> 10
A31: 1 | B31: Year 7 | C31: The week before | D31: Set up the class tab in the tracker: columns A to E (number, names, group, starting role) from the class list and seating plan. | E31: 10 | F31: estimate | G31: Teacher | H31: No | J31: No | L31: =IF(E31="","",IF(OR(AND(K31="Plan A",'All weeks'!$C$5="B"),AND(K31="Plan B",'All weeks'!$C$5="A")),0,IF(H31="Yes",E31,E31*IF(B31="Year 7",'All weeks'!$C$3,'All weeks'!$C$4)))) -> 10
A32: 1 | B32: Year 7 | C32: The week before | D32: Make 24 name cards from the class list and seating plan. | E32: 10 | F32: estimate | G32: Technician or assistant | H32: No | J32: No | L32: =IF(E32="","",IF(OR(AND(K32="Plan A",'All weeks'!$C$5="B"),AND(K32="Plan B",'All weeks'!$C$5="A")),0,IF(H32="Yes",E32,E32*IF(B32="Year 7",'All weeks'!$C$3,'All weeks'!$C$4)))) -> 10
A33: 1 | B33: Year 7 | C33: The day before | D33: Label 18 envelopes Stage 1, Stage 2, Stage 3 (3 per group) and put one puzzle card in each; keep the Stage 2 and 3 envelopes for the teacher desk. | E33: 5 | F33: kit card | G33: Technician or assistant | H33: No | J33: No | L33: =IF(E33="","",IF(OR(AND(K33="Plan A",'All weeks'!$C$5="B"),AND(K33="Plan B",'All weeks'!$C$5="A")),0,IF(H33="Yes",E33,E33*IF(B33="Year 7",'All weeks'!$C$3,'All weeks'!$C$4)))) -> 5
A34: 1 | B34: Year 7 | C34: On the day, before the lesson | D34: Set out name cards by the group seating plan and one set of role cards per table. | E34: 5 | F34: kit card | G34: Technician or assistant | H34: No | J34: No | L34: =IF(E34="","",IF(OR(AND(K34="Plan A",'All weeks'!$C$5="B"),AND(K34="Plan B",'All weeks'!$C$5="A")),0,IF(H34="Yes",E34,E34*IF(B34="Year 7",'All weeks'!$C$3,'All weeks'!$C$4)))) -> 5
A35: 1 | B35: Year 7 | C35: On the day, before the lesson | D35: Put out pencils (1 per student, spares on the teacher desk); place the sorted skills checks and surveys, logbooks, dictionaries and the 18 envelopes on the teacher desk. | E35: 3 | F35: estimate | G35: Technician or assistant | H35: No | J35: No | L35: =IF(E35="","",IF(OR(AND(K35="Plan A",'All weeks'!$C$5="B"),AND(K35="Plan B",'All weeks'!$C$5="A")),0,IF(H35="Yes",E35,E35*IF(B35="Year 7",'All weeks'!$C$3,'All weeks'!$C$4)))) -> 3
A36: 1 | B36: Year 7 | C36: Set-up by students in the lesson | D36: Clean-up led by the Safety Officer: puzzle cards back into their envelopes in stage order and returned to the teacher; logbooks collected into the class box. | E36: 1 | F36: estimate | G36: Students (roles) | H36: No | J36: No | L36: =IF(E36="","",IF(OR(AND(K36="Plan A",'All weeks'!$C$5="B"),AND(K36="Plan B",'All weeks'!$C$5="A")),0,IF(H36="Yes",E36,E36*IF(B36="Year 7",'All weeks'!$C$3,'All weeks'!$C$4)))) -> 1
A37: 1 | B37: Year 7 | C37: After the lesson | D37: Check the six envelope sets are complete and in stage order; put the class box of logbooks away. | E37: 3 | F37: estimate | G37: Technician or assistant | H37: No | J37: No | L37: =IF(E37="","",IF(OR(AND(K37="Plan A",'All weeks'!$C$5="B"),AND(K37="Plan B",'All weeks'!$C$5="A")),0,IF(H37="Yes",E37,E37*IF(B37="Year 7",'All weeks'!$C$3,'All weeks'!$C$4)))) -> 3
A38: 1 | B38: Year 7 | C38: After the lesson | D38: Read the exit tickets before Week 2; note who needs the Do Now recap and who is ready for Stretch. | E38: 10 | F38: estimate | G38: Teacher | H38: No | J38: No | L38: =IF(E38="","",IF(OR(AND(K38="Plan A",'All weeks'!$C$5="B"),AND(K38="Plan B",'All weeks'!$C$5="A")),0,IF(H38="Yes",E38,E38*IF(B38="Year 7",'All weeks'!$C$3,'All weeks'!$C$4)))) -> 10
A39: 1 | B39: Year 7 | C39: After the lesson | D39: Mark the skills checks out of 20 with the mark scheme within the week (no half marks; accept Chinese). | E39: 70 | F39: estimate | G39: Teacher | H39: No | J39: No | L39: =IF(E39="","",IF(OR(AND(K39="Plan A",'All weeks'!$C$5="B"),AND(K39="Plan B",'All weeks'!$C$5="A")),0,IF(H39="Yes",E39,E39*IF(B39="Year 7",'All weeks'!$C$3,'All weeks'!$C$4)))) -> 70
A40: 1 | B40: Year 7 | C40: After the lesson | D40: Enter skills check totals and the six survey scores per student in the tracker (columns I to O) and any access arrangements (column H); file the papers in the class assessment folder and do not return them. | E40: 25 | F40: estimate | G40: Technician or assistant | H40: No | J40: No | L40: =IF(E40="","",IF(OR(AND(K40="Plan A",'All weeks'!$C$5="B"),AND(K40="Plan B",'All weeks'!$C$5="A")),0,IF(H40="Yes",E40,E40*IF(B40="Year 7",'All weeks'!$C$3,'All weeks'!$C$4)))) -> 25
A41: 1 | B41: Year 7 | C41: After the lesson | D41: Enter question-by-question skills check marks on the tracker's Question_analysis tab. | E41: 15 | F41: estimate | G41: Technician or assistant | H41: No | J41: Optional | L41: =IF(E41="","",IF(OR(AND(K41="Plan A",'All weeks'!$C$5="B"),AND(K41="Plan B",'All weeks'!$C$5="A")),0,IF(H41="Yes",E41,E41*IF(B41="Year 7",'All weeks'!$C$3,'All weeks'!$C$4)))) -> 15
A42: 1 | B42: Year 8 | C42: 2 or more weeks before | D42: Order the kit: 8 black washable felt-tip pens (four brands, two of each), coffee filters, masking tape, 24 A4 folders, 49 sheets of white A4 card, A3 paper, laminating pouches (6 A4, 30 A5), 24 pencils and a class box; plain bar soap and baking soda if using the scene table. | E42: 15 | F42: estimate | G42: Technician or assistant | H42: Yes | I42: Pens: Week 3; folders and class box: Weeks 2 to 10 | J42: No | L42: =IF(E42="","",IF(OR(AND(K42="Plan A",'All weeks'!$C$5="B"),AND(K42="Plan B",'All weeks'!$C$5="A")),0,IF(H42="Yes",E42,E42*IF(B42="Year 7",'All weeks'!$C$3,'All weeks'!$C$4)))) -> 15
A43: 1 | B43: Year 8 | C43: 2 or more weeks before | D43: Book reprographics printing for Weeks 1 to 5 and print only from the designs rebuilt after the language pass (discard any copies printed earlier). | E43: 10 | F43: estimate | G43: Teacher | H43: Yes | J43: No | L43: =IF(E43="","",IF(OR(AND(K43="Plan A",'All weeks'!$C$5="B"),AND(K43="Plan B",'All weeks'!$C$5="A")),0,IF(H43="Yes",E43,E43*IF(B43="Year 7",'All weeks'!$C$3,'All weeks'!$C$4)))) -> 10
A44: 1 | B44: Year 8 | C44: 2 or more weeks before | D44: Check the Skills Check master is final (native-speaker fixes made) before the print run, then freeze it unchanged until Week 10. | E44: 5 | F44: estimate | G44: Teacher | H44: Yes | I44: Week 10 (same master) | J44: No | L44: =IF(E44="","",IF(OR(AND(K44="Plan A",'All weeks'!$C$5="B"),AND(K44="Plan B",'All weeks'!$C$5="A")),0,IF(H44="Yes",E44,E44*IF(B44="Year 7",'All weeks'!$C$3,'All weeks'!$C$4)))) -> 5
A45: 1 | B45: Year 8 | C45: 2 or more weeks before | D45: Print, fold and staple My Science Dictionary, Year 8 (28 per class: 24 plus 4 spares, 7 A4 sheets each, double-sided, 90 gsm) and the Scientist's Logbooks (24). | E45: 30 | F45: estimate | G45: Reprographics | H45: No | I45: Weeks 2 to 10 | J45: No | L45: =IF(E45="","",IF(OR(AND(K45="Plan A",'All weeks'!$C$5="B"),AND(K45="Plan B",'All weeks'!$C$5="A")),0,IF(H45="Yes",E45,E45*IF(B45="Year 7",'All weeks'!$C$3,'All weeks'!$C$4)))) -> 30
A46: 1 | B46: Year 8 | C46: The week before | D46: Ask the school nurse or form tutors for the allergy list (needed for the Week 4 powders). | E46: 5 | F46: estimate | G46: Teacher | H46: Yes | I46: Weeks 4 and 5 | J46: No | L46: =IF(E46="","",IF(OR(AND(K46="Plan A",'All weeks'!$C$5="B"),AND(K46="Plan B",'All weeks'!$C$5="A")),0,IF(H46="Yes",E46,E46*IF(B46="Year 7",'All weeks'!$C$3,'All weeks'!$C$4)))) -> 5
A47: 1 | B47: Year 8 | C47: The week before | D47: Print the language support pack: 3 A3 posters (Instruction words, Classroom language side B, Think in any language), the A4 Science Detectives frame poster, 6 sets of frame cards (24 A4 sheets), 6 role card sheets and 30 two-sided classroom language cards. | E47: 15 | F47: estimate | G47: Reprographics | H47: No | I47: All term | J47: No | L47: =IF(E47="","",IF(OR(AND(K47="Plan A",'All weeks'!$C$5="B"),AND(K47="Plan B",'All weeks'!$C$5="A")),0,IF(H47="Yes",E47,E47*IF(B47="Year 7",'All weeks'!$C$3,'All weeks'!$C$4)))) -> 15
A48: 1 | B48: Year 8 | C48: The week before | D48: Laminate and cut the role cards (6 A4 sheets into 36 cards) and the 30 classroom language cards; cut the 6 sets of frame cards. | E48: 50 | F48: estimate | G48: Technician or assistant | H48: No | I48: All term | J48: No | L48: =IF(E48="","",IF(OR(AND(K48="Plan A",'All weeks'!$C$5="B"),AND(K48="Plan B",'All weeks'!$C$5="A")),0,IF(H48="Yes",E48,E48*IF(B48="Year 7",'All weeks'!$C$3,'All weeks'!$C$4)))) -> 50
A49: 1 | B49: Year 8 | C49: The week before | D49: Print the worksheets: 24 copies, pages 1 and 2 back to back and page 3 on its own sheet (48 A4 sheets). | E49: 5 | F49: estimate | G49: Reprographics | H49: No | J49: No | L49: =IF(E49="","",IF(OR(AND(K49="Plan A",'All weeks'!$C$5="B"),AND(K49="Plan B",'All weeks'!$C$5="A")),0,IF(H49="Yes",E49,E49*IF(B49="Year 7",'All weeks'!$C$3,'All weeks'!$C$4)))) -> 5
A50: 1 | B50: Year 8 | C50: The week before | D50: Run the pen pre-test (Case Bible Section 11): cut 4 coffee-filter strips 2 cm by 10 cm, pencil line 2 cm up, one dot per pen, stand in cups of water 1 cm deep for 6 to 8 minutes; check four clearly different patterns; choose pen B; cover brand names with masking tape and label A to D; record on the Teacher Pre-test Record; keep the dried strips. The Teacher Guide puts this in the Week 1 week; do it before the lesson if the pen-B note is wanted for the scene table or a slide photo. | E50: 20 | F50: teacher guide | G50: Teacher | H50: Yes | I50: Week 3 (pens, answer key) | J50: No | L50: =IF(E50="","",IF(OR(AND(K50="Plan A",'All weeks'!$C$5="B"),AND(K50="Plan B",'All weeks'!$C$5="A")),0,IF(H50="Yes",E50,E50*IF(B50="Year 7",'All weeks'!$C$3,'All weeks'!$C$4)))) -> 20
A51: 1 | B51: Year 8 | C51: The week before | D51: Write the display note with pen B on plain white card (exact text, snowflake doodle after 'Sorry!'); photograph it for Slide 5 if wanted. | E51: 5 | F51: estimate | G51: Teacher | H51: Yes | I51: Week 3 Hook | J51: No | L51: =IF(E51="","",IF(OR(AND(K51="Plan A",'All weeks'!$C$5="B"),AND(K51="Plan B",'All weeks'!$C$5="A")),0,IF(H51="Yes",E51,E51*IF(B51="Year 7",'All weeks'!$C$3,'All weeks'!$C$4)))) -> 5
A52: 1 | B52: Year 8 | C52: The week before | D52: Print teacher copies: kit card (A5), Skills Check mark scheme (2 pages) and Teacher Pre-test Record. | E52: 5 | F52: estimate | G52: Teacher | H52: Yes | J52: No | L52: =IF(E52="","",IF(OR(AND(K52="Plan A",'All weeks'!$C$5="B"),AND(K52="Plan B",'All weeks'!$C$5="A")),0,IF(H52="Yes",E52,E52*IF(B52="Year 7",'All weeks'!$C$3,'All weeks'!$C$4)))) -> 5
A53: 1 | B53: Year 8 | C53: The week before | D53: Plan 6 fixed groups of 4, seating each Band 1 student beside a Band 3 language buddy, and make the name cards. | E53: 15 | F53: estimate | G53: Teacher | H53: No | I53: Weeks 2 to 5 (fixed groups) | J53: No | L53: =IF(E53="","",IF(OR(AND(K53="Plan A",'All weeks'!$C$5="B"),AND(K53="Plan B",'All weeks'!$C$5="A")),0,IF(H53="Yes",E53,E53*IF(B53="Year 7",'All weeks'!$C$3,'All weeks'!$C$4)))) -> 15
A54: 1 | B54: Year 8 | C54: The week before | D54: Label the class box with a section for each group. | E54: 5 | F54: estimate | G54: Technician or assistant | H54: No | I54: Weeks 2 to 10 | J54: No | L54: =IF(E54="","",IF(OR(AND(K54="Plan A",'All weeks'!$C$5="B"),AND(K54="Plan B",'All weeks'!$C$5="A")),0,IF(H54="Yes",E54,E54*IF(B54="Year 7",'All weeks'!$C$3,'All weeks'!$C$4)))) -> 5
A55: 1 | B55: Year 8 | C55: The week before | D55: Print the optional scene table sign (A5) and the true-size footprint at 100% scale; check the footprint measures 24 cm with a ruler. | E55: 5 | F55: estimate | G55: Technician or assistant | H55: Yes | J55: Optional | L55: =IF(E55="","",IF(OR(AND(K55="Plan A",'All weeks'!$C$5="B"),AND(K55="Plan B",'All weeks'!$C$5="A")),0,IF(H55="Yes",E55,E55*IF(B55="Year 7",'All weeks'!$C$3,'All weeks'!$C$4)))) -> 5
A56: 1 | B56: Year 8 | C56: The day before | D56: Kit card prep: print and collate the case files, one per student (24), in order: cover, briefing with sign-in sheet, scene map, suspect cards, evidence log, in A4 folders with a dictionary tucked inside; print the skills checks and surveys in class order (cut the survey sheets in half); set out groups of 4 with name cards. | E56: 25 | F56: kit card | G56: Technician or assistant | H56: No | I56: Case files: Weeks 2 to 10 | J56: No | L56: =IF(E56="","",IF(OR(AND(K56="Plan A",'All weeks'!$C$5="B"),AND(K56="Plan B",'All weeks'!$C$5="A")),0,IF(H56="Yes",E56,E56*IF(B56="Year 7",'All weeks'!$C$3,'All weeks'!$C$4)))) -> 25
A57: 1 | B57: Year 8 | C57: The day before | D57: Put up the three A3 language posters, the A4 frame poster and the A3 scene map; put a frame card set and a role card set on each group table. | E57: 10 | F57: estimate | G57: Technician or assistant | H57: Yes | I57: All term | J57: No | L57: =IF(E57="","",IF(OR(AND(K57="Plan A",'All weeks'!$C$5="B"),AND(K57="Plan B",'All weeks'!$C$5="A")),0,IF(H57="Yes",E57,E57*IF(B57="Year 7",'All weeks'!$C$3,'All weeks'!$C$4)))) -> 10
A58: 1 | B58: Year 8 | C58: On the day, before the lesson | D58: Make the optional scene liquid: grate about 1 teaspoon of plain bar soap into 200 ml warm water and stir until cloudy; make the baking soda solution; mix equal amounts and pour a little into the saucer. | E58: 10 | F58: estimate | G58: Teacher | H58: Yes | J58: Optional | L58: =IF(E58="","",IF(OR(AND(K58="Plan A",'All weeks'!$C$5="B"),AND(K58="Plan B",'All weeks'!$C$5="A")),0,IF(H58="Yes",E58,E58*IF(B58="Year 7",'All weeks'!$C$3,'All weeks'!$C$4)))) -> 10
A59: 1 | B59: Year 8 | C59: On the day, before the lesson | D59: Set up the optional scene table at the front: glass, pen-B note, teaspoon of baking soda on a dark tray, saucer of scene liquid, 24 cm paper footprint and the do-not-touch sign. | E59: 5 | F59: kit card | G59: Teacher | H59: No | J59: Optional | L59: =IF(E59="","",IF(OR(AND(K59="Plan A",'All weeks'!$C$5="B"),AND(K59="Plan B",'All weeks'!$C$5="A")),0,IF(H59="Yes",E59,E59*IF(B59="Year 7",'All weeks'!$C$3,'All weeks'!$C$4)))) -> 5
A60: 1 | B60: Year 8 | C60: After the lesson | D60: Clear the scene table: pour away the scene liquid, wash the glass, saucer and tray; keep the note and pens A to D for Week 3 (pen B never left on a student table). | E60: 5 | F60: estimate | G60: Technician or assistant | H60: No | I60: Note and pens: Week 3 | J60: Optional | L60: =IF(E60="","",IF(OR(AND(K60="Plan A",'All weeks'!$C$5="B"),AND(K60="Plan B",'All weeks'!$C$5="A")),0,IF(H60="Yes",E60,E60*IF(B60="Year 7",'All weeks'!$C$3,'All weeks'!$C$4)))) -> 5
A61: 1 | B61: Year 8 | C61: After the lesson | D61: Check the case files and logbooks are in the class box, filed by group, and that every file has its suspect cards for the Week 2 Do Now. | E61: 5 | F61: estimate | G61: Teacher | H61: No | I61: Weeks 2 to 10 | J61: No | L61: =IF(E61="","",IF(OR(AND(K61="Plan A",'All weeks'!$C$5="B"),AND(K61="Plan B",'All weeks'!$C$5="A")),0,IF(H61="Yes",E61,E61*IF(B61="Year 7",'All weeks'!$C$3,'All weeks'!$C$4)))) -> 5
A62: 1 | B62: Year 8 | C62: After the lesson | D62: Mark the skills checks with the mark scheme within the week (no half marks; accept Chinese; ignore spelling if the science is clear). | E62: 70 | F62: estimate | G62: Teacher | H62: No | J62: No | L62: =IF(E62="","",IF(OR(AND(K62="Plan A",'All weeks'!$C$5="B"),AND(K62="Plan B",'All weeks'!$C$5="A")),0,IF(H62="Yes",E62,E62*IF(B62="Year 7",'All weeks'!$C$3,'All weeks'!$C$4)))) -> 70
A63: 1 | B63: Year 8 | C63: After the lesson | D63: Enter the tracker Week 1 columns (A to E, H, I skills check, J to O survey) and file the papers in the class assessment folder, noting where for the handover note; do not return or go through them. | E63: 20 | F63: estimate | G63: Teacher | H63: No | I63: Week 10 comparison | J63: No | L63: =IF(E63="","",IF(OR(AND(K63="Plan A",'All weeks'!$C$5="B"),AND(K63="Plan B",'All weeks'!$C$5="A")),0,IF(H63="Yes",E63,E63*IF(B63="Year 7",'All weeks'!$C$3,'All weeks'!$C$4)))) -> 20
A64: 1 | B64: Year 8 | C64: After the lesson | D64: Read the exit tickets to plan the Week 2 Do Now recap and who is ready for Stretch. | E64: 10 | F64: estimate | G64: Teacher | H64: No | J64: No | L64: =IF(E64="","",IF(OR(AND(K64="Plan A",'All weeks'!$C$5="B"),AND(K64="Plan B",'All weeks'!$C$5="A")),0,IF(H64="Yes",E64,E64*IF(B64="Year 7",'All weeks'!$C$3,'All weeks'!$C$4)))) -> 10
A65: 2 | B65: Year 7 | C65: 2 or more weeks before | D65: Order or gather the mystery cup contents and 24 opaque paper cups: 3 marbles, cotton ball, coin, paper clip, teaspoon of dry rice, eraser, dice, small bell, bottle cap, small wooden block; masking tape and a marker | E65: 10 | F65: estimate | G65: Technician or assistant | H65: Yes | J65: No | L65: =IF(E65="","",IF(OR(AND(K65="Plan A",'All weeks'!$C$5="B"),AND(K65="Plan B",'All weeks'!$C$5="A")),0,IF(H65="Yes",E65,E65*IF(B65="Year 7",'All weeks'!$C$3,'All weeks'!$C$4)))) -> 10
A66: 2 | B66: Year 7 | C66: 2 or more weeks before | D66: Book the print job with reprographics: worksheets (24 per class, 4 A4 pages double-sided = 48 sheets, collated), A3 Galileo storyboard poster, kit card (teacher copy, A5); optional 6 A4 storyboard copies. Print only from the Year 7 designs rebuilt after the language pass and discard any copies printed earlier | E66: 5 | F66: estimate | G66: Reprographics | H66: Yes | J66: No | L66: =IF(E66="","",IF(OR(AND(K66="Plan A",'All weeks'!$C$5="B"),AND(K66="Plan B",'All weeks'!$C$5="A")),0,IF(H66="Yes",E66,E66*IF(B66="Year 7",'All weeks'!$C$3,'All weeks'!$C$4)))) -> 5
A67: 2 | B67: Year 7 | C67: The week before | D67: Make 12 mystery cups: one object in each opaque cup, second cup upside down on top (rim to rim), tape all round with masking tape, label A to L underneath; keep the key on the teacher desk | E67: 15 | F67: kit card | G67: Technician or assistant | H67: Yes | I67: Kept in the teacher box for future years | J67: No | L67: =IF(E67="","",IF(OR(AND(K67="Plan A",'All weeks'!$C$5="B"),AND(K67="Plan B",'All weeks'!$C$5="A")),0,IF(H67="Yes",E67,E67*IF(B67="Year 7",'All weeks'!$C$3,'All weeks'!$C$4)))) -> 15
A68: 2 | B68: Year 7 | C68: The week before | D68: Print the question sort cards on A4 white card: 6 sets x 2 sheets = 12 sheets, single-sided | E68: 5 | F68: estimate | G68: Reprographics | H68: Yes | J68: No | L68: =IF(E68="","",IF(OR(AND(K68="Plan A",'All weeks'!$C$5="B"),AND(K68="Plan B",'All weeks'!$C$5="A")),0,IF(H68="Yes",E68,E68*IF(B68="Year 7",'All weeks'!$C$3,'All weeks'!$C$4)))) -> 5
A69: 2 | B69: Year 7 | C69: The week before | D69: Cut out the question sort cards: 6 sets x 14 cards = 84 business-card-size cards (stack the sheets on a guillotine) | E69: 15 | F69: estimate | G69: Technician or assistant | H69: Yes | J69: No | L69: =IF(E69="","",IF(OR(AND(K69="Plan A",'All weeks'!$C$5="B"),AND(K69="Plan B",'All weeks'!$C$5="A")),0,IF(H69="Yes",E69,E69*IF(B69="Year 7",'All weeks'!$C$3,'All weeks'!$C$4)))) -> 15
A70: 2 | B70: Year 7 | C70: The week before | D70: Put each set (12 question cards + 2 header cards) in an envelope, one per group | E70: 5 | F70: kit card | G70: Technician or assistant | H70: Yes | J70: No | L70: =IF(E70="","",IF(OR(AND(K70="Plan A",'All weeks'!$C$5="B"),AND(K70="Plan B",'All weeks'!$C$5="A")),0,IF(H70="Yes",E70,E70*IF(B70="Year 7",'All weeks'!$C$3,'All weeks'!$C$4)))) -> 5
A71: 2 | B71: Year 7 | C71: The week before | D71: Find a hardback book (about A4) and practise the paper-on-top drop once, with a sheet smaller than the cover | E71: 5 | F71: estimate | G71: Teacher | H71: Yes | J71: No | L71: =IF(E71="","",IF(OR(AND(K71="Plan A",'All weeks'!$C$5="B"),AND(K71="Plan B",'All weeks'!$C$5="A")),0,IF(H71="Yes",E71,E71*IF(B71="Year 7",'All weeks'!$C$3,'All weeks'!$C$4)))) -> 5
A72: 2 | B72: Year 7 | C72: The day before | D72: Put up the A3 Galileo storyboard poster | E72: 2 | F72: estimate | G72: Technician or assistant | H72: Yes | J72: No | L72: =IF(E72="","",IF(OR(AND(K72="Plan A",'All weeks'!$C$5="B"),AND(K72="Plan B",'All weeks'!$C$5="A")),0,IF(H72="Yes",E72,E72*IF(B72="Year 7",'All weeks'!$C$3,'All weeks'!$C$4)))) -> 2
A73: 2 | B73: Year 7 | C73: On the day, before the lesson | D73: Set out before students arrive: 2 mystery cups per table (different cups for neighbouring groups), role cards, frame cards and pencils; sort card envelopes, worksheets, book, 3 demo sheets and the kit card with the cup key on the teacher desk | E73: 5 | F73: estimate | G73: Teacher | H73: No | J73: No | L73: =IF(E73="","",IF(OR(AND(K73="Plan A",'All weeks'!$C$5="B"),AND(K73="Plan B",'All weeks'!$C$5="A")),0,IF(H73="Yes",E73,E73*IF(B73="Year 7",'All weeks'!$C$3,'All weeks'!$C$4)))) -> 5
A74: 2 | B74: Year 7 | C74: After the lesson | D74: Clean-up (Safety Officer leads): count each sort card set back to 12 cards plus 2 headers into its envelope; return mystery cups to the teacher box; logbooks into the class box | E74: 3 | F74: estimate | G74: Students (roles) | H74: No | J74: No | L74: =IF(E74="","",IF(OR(AND(K74="Plan A",'All weeks'!$C$5="B"),AND(K74="Plan B",'All weeks'!$C$5="A")),0,IF(H74="Yes",E74,E74*IF(B74="Year 7",'All weeks'!$C$3,'All weeks'!$C$4)))) -> 3
A75: 2 | B75: Year 7 | C75: After the lesson | D75: Check every mystery cup's tape is intact and re-tape any loose cup before the next class | E75: 3 | F75: estimate | G75: Technician or assistant | H75: No | J75: No | L75: =IF(E75="","",IF(OR(AND(K75="Plan A",'All weeks'!$C$5="B"),AND(K75="Plan B",'All weeks'!$C$5="A")),0,IF(H75="Yes",E75,E75*IF(B75="Year 7",'All weeks'!$C$3,'All weeks'!$C$4)))) -> 3
A76: 2 | B76: Year 7 | C76: After the lesson | D76: Read the exit tickets before the next lesson: note who needs the Do Now recap and who is ready for Stretch; note the groups that made three or more sort errors (checked in class) | E76: 10 | F76: estimate | G76: Teacher | H76: No | J76: No | L76: =IF(E76="","",IF(OR(AND(K76="Plan A",'All weeks'!$C$5="B"),AND(K76="Plan B",'All weeks'!$C$5="A")),0,IF(H76="Yes",E76,E76*IF(B76="Year 7",'All weeks'!$C$3,'All weeks'!$C$4)))) -> 10
A77: 2 | B77: Year 7 | C77: After the lesson | D77: Record a language band (1, 2 or 3) for each student in tracker column G, now that two lessons have been taught | E77: 10 | F77: estimate | G77: Teacher | H77: No | J77: No | L77: =IF(E77="","",IF(OR(AND(K77="Plan A",'All weeks'!$C$5="B"),AND(K77="Plan B",'All weeks'!$C$5="A")),0,IF(H77="Yes",E77,E77*IF(B77="Year 7",'All weeks'!$C$3,'All weeks'!$C$4)))) -> 10
A78: 2 | B78: Year 8 | C78: 2 or more weeks before | D78: Order the kit on the outline's Buy list (Teacher Guide prep calendar, before Week 1): soft pencils 2B to 4B (24), clear sticky tape (6 rolls), A4 white card (12 sheets per class for the record cards) | E78: 10 | F78: estimate | G78: Technician or assistant | H78: Yes | I78: Tape rolls reused in Week 3 | J78: No | L78: =IF(E78="","",IF(OR(AND(K78="Plan A",'All weeks'!$C$5="B"),AND(K78="Plan B",'All weeks'!$C$5="A")),0,IF(H78="Yes",E78,E78*IF(B78="Year 7",'All weeks'!$C$3,'All weeks'!$C$4)))) -> 10
A79: 2 | B79: Year 8 | C79: 2 or more weeks before | D79: Send the print job to reprographics (printing for Weeks 1 to 5 is booked before Week 1): worksheets, 24 per class (3 A4 pages, pages 1 and 2 back to back and page 3 on its own sheet = 48 sheets); kit card, 1 A5 teacher copy. Use only the designs rebuilt after the language pass | E79: 5 | F79: estimate | G79: Reprographics | H79: Yes | J79: No | L79: =IF(E79="","",IF(OR(AND(K79="Plan A",'All weeks'!$C$5="B"),AND(K79="Plan B",'All weeks'!$C$5="A")),0,IF(H79="Yes",E79,E79*IF(B79="Year 7",'All weeks'!$C$3,'All weeks'!$C$4)))) -> 5
A80: 2 | B80: Year 8 | C80: The week before | D80: Gather from the prep room: 12 magnifying glasses, 6 trays, cloths for wiping tables (number not stated), 24 sheets of scrap paper per class (one-side-used is fine), paper towels or wet wipes; check the visualiser works and the room has a sink with soap for hand washing | E80: 10 | F80: estimate | G80: Technician or assistant | H80: Yes | J80: No | L80: =IF(E80="","",IF(OR(AND(K80="Plan A",'All weeks'!$C$5="B"),AND(K80="Plan B",'All weeks'!$C$5="A")),0,IF(H80="Yes",E80,E80*IF(B80="Year 7",'All weeks'!$C$3,'All weeks'!$C$4)))) -> 10
A81: 2 | B81: Year 8 | C81: The week before | D81: Kit card teacher prep, printing (Teacher Guide prep calendar, Week 1 row): print the fingerprint record cards on A4 white card, 2 per sheet (A5 landscape, single-sided), and cut in half: 12 sheets = 24 cards per class; print the Fingerprint File, 7 A4 single-sided copies per class (6 groups + 1 display). Check the scene print is clearly a loop but smudged at the centre and no pattern names are on the sheet (Case Bible Section 12: 10 minutes) | E81: 10 | F81: lesson file | G81: Technician or assistant | H81: Yes | I81: Record cards stay in the case files | J81: No | L81: =IF(E81="","",IF(OR(AND(K81="Plan A",'All weeks'!$C$5="B"),AND(K81="Plan B",'All weeks'!$C$5="A")),0,IF(H81="Yes",E81,E81*IF(B81="Year 7",'All weeks'!$C$3,'All weeks'!$C$4)))) -> 10
A82: 2 | B82: Year 8 | C82: The week before | D82: Check every case file has its suspect cards (the Do Now uses them) and its evidence log (Week 1 lesson file note) | E82: 5 | F82: estimate | G82: Teacher | H82: No | J82: No | L82: =IF(E82="","",IF(OR(AND(K82="Plan A",'All weeks'!$C$5="B"),AND(K82="Plan B",'All weeks'!$C$5="A")),0,IF(H82="Yes",E82,E82*IF(B82="Year 7",'All weeks'!$C$3,'All weeks'!$C$4)))) -> 5
A83: 2 | B83: Year 8 | C83: The week before | D83: Practise one pencil-and-tape print (lots of graphite, gentle press, no sliding) before demonstrating it under the visualiser | E83: 5 | F83: estimate | G83: Teacher | H83: Yes | J83: Optional | L83: =IF(E83="","",IF(OR(AND(K83="Plan A",'All weeks'!$C$5="B"),AND(K83="Plan B",'All weeks'!$C$5="A")),0,IF(H83="Yes",E83,E83*IF(B83="Year 7",'All weeks'!$C$3,'All weeks'!$C$4)))) -> 5
A84: 2 | B84: Year 8 | C84: The day before | D84: Plan the seating so each Band 1 student sits beside a Band 3 language buddy, who holds the Language buddy card | E84: 5 | F84: estimate | G84: Teacher | H84: No | J84: No | L84: =IF(E84="","",IF(OR(AND(K84="Plan A",'All weeks'!$C$5="B"),AND(K84="Plan B",'All weeks'!$C$5="A")),0,IF(H84="Yes",E84,E84*IF(B84="Year 7",'All weeks'!$C$3,'All weeks'!$C$4)))) -> 5
A85: 2 | B85: Year 8 | C85: The day before | D85: Optional display (kit card; Case Bible Section 12): cut the scene print from a printed Fingerprint File and tape it onto a real drinking glass | E85: 2 | F85: estimate | G85: Technician or assistant | H85: Yes | J85: Optional | L85: =IF(E85="","",IF(OR(AND(K85="Plan A",'All weeks'!$C$5="B"),AND(K85="Plan B",'All weeks'!$C$5="A")),0,IF(H85="Yes",E85,E85*IF(B85="Year 7",'All weeks'!$C$3,'All weeks'!$C$4)))) -> 2
A86: 2 | B86: Year 8 | C86: On the day, before the lesson | D86: Kit card teacher prep, before students arrive (the kit card gives about 15 minutes for all teacher prep, including the printing above): draw the tally table on the board with rows labelled as on Slide 9 (Loop 箕形纹 / Whorl 斗形纹 / Arch 弓形纹 / Total 总数); set out 6 trays, each with 4 soft pencils, 1 roll of clear tape, 4 sheets of scrap paper, 4 record cards, 2 magnifying glasses and a few paper towels or wet wipes; case files, role cards and frame cards on the tables; worksheets and Fingerprint Files on the teacher desk (the Fingerprint Files go out at minute 14 of the Do phase); visualiser on | E86: 5 | F86: kit card | G86: Teacher | H86: No | J86: No | L86: =IF(E86="","",IF(OR(AND(K86="Plan A",'All weeks'!$C$5="B"),AND(K86="Plan B",'All weeks'!$C$5="A")),0,IF(H86="Yes",E86,E86*IF(B86="Year 7",'All weeks'!$C$3,'All weeks'!$C$4)))) -> 5
A87: 2 | B87: Year 8 | C87: After the lesson | D87: Clean-up (kit card; Safety Officer leads): record cards into case files; tape and pencils back in the tray; wipe tables; everyone washes hands; Fingerprint Files collected | E87: 3 | F87: estimate | G87: Students (roles) | H87: No | J87: No | L87: =IF(E87="","",IF(OR(AND(K87="Plan A",'All weeks'!$C$5="B"),AND(K87="Plan B",'All weeks'!$C$5="A")),0,IF(H87="Yes",E87,E87*IF(B87="Year 7",'All weeks'!$C$3,'All weeks'!$C$4)))) -> 3
A88: 2 | B88: Year 8 | C88: After the lesson | D88: Between classes: count pencils and tape back; refill each tray with 4 sheets of scrap paper and 4 record cards; replace any Fingerprint File that has been written on | E88: 5 | F88: estimate | G88: Technician or assistant | H88: No | J88: No | L88: =IF(E88="","",IF(OR(AND(K88="Plan A",'All weeks'!$C$5="B"),AND(K88="Plan B",'All weeks'!$C$5="A")),0,IF(H88="Yes",E88,E88*IF(B88="Year 7",'All weeks'!$C$3,'All weeks'!$C$4)))) -> 5
A89: 2 | B89: Year 8 | C89: After the lesson | D89: Read the exit tickets (common vs rare as evidence) and check a sample of record cards for correct classification; note who needs the next Do Now recap; case files and logbooks into the class box | E89: 10 | F89: estimate | G89: Teacher | H89: No | J89: No | L89: =IF(E89="","",IF(OR(AND(K89="Plan A",'All weeks'!$C$5="B"),AND(K89="Plan B",'All weeks'!$C$5="A")),0,IF(H89="Yes",E89,E89*IF(B89="Year 7",'All weeks'!$C$3,'All weeks'!$C$4)))) -> 10
A90: 2 | B90: Year 8 | C90: After the lesson | D90: After the last class: return the magnifying glasses, trays and cloths to the prep room; keep the 6 tape rolls for Week 3 | E90: 3 | F90: estimate | G90: Technician or assistant | H90: Yes | I90: Tape rolls reused in Week 3 | J90: No | L90: =IF(E90="","",IF(OR(AND(K90="Plan A",'All weeks'!$C$5="B"),AND(K90="Plan B",'All weeks'!$C$5="A")),0,IF(H90="Yes",E90,E90*IF(B90="Year 7",'All weeks'!$C$3,'All weeks'!$C$4)))) -> 3
A91: 3 | B91: Year 7 | C91: The week before | D91: Print the spinner template on A4 thin card (160 gsm) at 100% scale, not 'fit to page': 9 sheets per class (1 per group plus 3 spares); check the 1 cm square measures 1 cm | E91: 5 | F91: kit card | G91: Technician or assistant | H91: Yes | I91: Week 4 | J91: No | L91: =IF(E91="","",IF(OR(AND(K91="Plan A",'All weeks'!$C$5="B"),AND(K91="Plan B",'All weeks'!$C$5="A")),0,IF(H91="Yes",E91,E91*IF(B91="Year 7",'All weeks'!$C$3,'All weeks'!$C$4)))) -> 5
A92: 3 | B92: Year 7 | C92: The week before | D92: Send the worksheet to reprographics: 24 copies per class, 5 A4 pages double-sided (72 sheets), black and white; use only the designs rebuilt after the language pass | E92: 5 | F92: estimate | G92: Reprographics | H92: Yes | J92: No | L92: =IF(E92="","",IF(OR(AND(K92="Plan A",'All weeks'!$C$5="B"),AND(K92="Plan B",'All weeks'!$C$5="A")),0,IF(H92="Yes",E92,E92*IF(B92="Year 7",'All weeks'!$C$3,'All weeks'!$C$4)))) -> 5
A93: 3 | B93: Year 7 | C93: The week before | D93: Print the odd-one-out group sheet (6 A4 landscape sheets, single-sided) and cut each into four A6 cards A to D; keep each set of four together | E93: 10 | F93: estimate | G93: Technician or assistant | H93: Yes | J93: No | L93: =IF(E93="","",IF(OR(AND(K93="Plan A",'All weeks'!$C$5="B"),AND(K93="Plan B",'All weeks'!$C$5="A")),0,IF(H93="Yes",E93,E93*IF(B93="Year 7",'All weeks'!$C$3,'All weeks'!$C$4)))) -> 10
A94: 3 | B94: Year 7 | C94: The week before | D94: Print one copy of the kit card (A5) for the teacher | E94: 2 | F94: estimate | G94: Teacher | H94: Yes | J94: No | L94: =IF(E94="","",IF(OR(AND(K94="Plan A",'All weeks'!$C$5="B"),AND(K94="Plan B",'All weeks'!$C$5="A")),0,IF(H94="Yes",E94,E94*IF(B94="Year 7",'All weeks'!$C$3,'All weeks'!$C$4)))) -> 2
A95: 3 | B95: Year 7 | C95: The week before | D95: Measure and mark 2.0 m and 1.8 m above the floor at six stations with a metre stick and masking tape; label the lower strip '1.8 m'; choose walls away from windows, fans and air-conditioning vents | E95: 10 | F95: kit card | G95: Technician or assistant | H95: Yes | I95: Week 4 | J95: No | L95: =IF(E95="","",IF(OR(AND(K95="Plan A",'All weeks'!$C$5="B"),AND(K95="Plan B",'All weeks'!$C$5="A")),0,IF(H95="Yes",E95,E95*IF(B95="Year 7",'All weeks'!$C$3,'All weeks'!$C$4)))) -> 10
A96: 3 | B96: Year 7 | C96: The week before | D96: Make one S (4 cm) and one L (8 cm) spinner, each with one paper clip, for the Hook demo and test them once from the 2 m mark | E96: 10 | F96: kit card | G96: Teacher | H96: Yes | J96: No | L96: =IF(E96="","",IF(OR(AND(K96="Plan A",'All weeks'!$C$5="B"),AND(K96="Plan B",'All weeks'!$C$5="A")),0,IF(H96="Yes",E96,E96*IF(B96="Year 7",'All weeks'!$C$3,'All weeks'!$C$4)))) -> 10
A97: 3 | B97: Year 7 | C97: The day before | D97: Label six A5 envelopes with the group names | E97: 5 | F97: estimate | G97: Technician or assistant | H97: No | I97: Week 4 | J97: No | L97: =IF(E97="","",IF(OR(AND(K97="Plan A",'All weeks'!$C$5="B"),AND(K97="Plan B",'All weeks'!$C$5="A")),0,IF(H97="Yes",E97,E97*IF(B97="Year 7",'All weeks'!$C$3,'All weeks'!$C$4)))) -> 5
A98: 3 | B98: Year 7 | C98: On the day, before the lesson | D98: Set out one kit tray per group (1 template sheet, 2 scissors, 4 paper clips, 1 stopwatch, 1 metre stick, labelled envelope); put the 3 spare sheets, demo spinners, worksheets and odd-one-out card sets on the teacher desk; check the wall marks are stuck and the floor below is clear | E98: 10 | F98: estimate | G98: Technician or assistant | H98: No | J98: No | L98: =IF(E98="","",IF(OR(AND(K98="Plan A",'All weeks'!$C$5="B"),AND(K98="Plan B",'All weeks'!$C$5="A")),0,IF(H98="Yes",E98,E98*IF(B98="Year 7",'All weeks'!$C$3,'All weeks'!$C$4)))) -> 10
A99: 3 | B99: Year 7 | C99: After the lesson | D99: Collect the six envelopes, check each holds the S, M and L spinners, and store them with the logbooks in the class box for Week 4 | E99: 5 | F99: estimate | G99: Teacher | H99: No | I99: Week 4 | J99: No | L99: =IF(E99="","",IF(OR(AND(K99="Plan A",'All weeks'!$C$5="B"),AND(K99="Plan B",'All weeks'!$C$5="A")),0,IF(H99="Yes",E99,E99*IF(B99="Year 7",'All weeks'!$C$3,'All weeks'!$C$4)))) -> 5
A100: 3 | B100: Year 7 | C100: After the lesson | D100: Check 12 scissors and 6 stopwatches are back in the tray, collect the odd-one-out card sets, return kit and metre sticks to the prep room and clear paper scraps to recycling | E100: 5 | F100: estimate | G100: Technician or assistant | H100: No | J100: No | L100: =IF(E100="","",IF(OR(AND(K100="Plan A",'All weeks'!$C$5="B"),AND(K100="Plan B",'All weeks'!$C$5="A")),0,IF(H100="Yes",E100,E100*IF(B100="Year 7",'All weeks'!$C$3,'All weeks'!$C$4)))) -> 5
A101: 3 | B101: Year 7 | C101: After the lesson | D101: Read the exit tickets (IV, DV and one control variable) to plan the Week 4 Do Now recap and spot who is ready for Stretch | E101: 10 | F101: estimate | G101: Teacher | H101: No | J101: No | L101: =IF(E101="","",IF(OR(AND(K101="Plan A",'All weeks'!$C$5="B"),AND(K101="Plan B",'All weeks'!$C$5="A")),0,IF(H101="Yes",E101,E101*IF(B101="Year 7",'All weeks'!$C$3,'All weeks'!$C$4)))) -> 10
A102: 3 | B102: Year 8 | C102: 2 or more weeks before | D102: Buy the group pens: 24 black washable felt-tip pens (6 sets of A to D) in the same four brands as the pre-test pens; check there are enough white coffee filters for 44 strips per class (filters are on the before-Week 1 buy list) | E102: 10 | F102: estimate | G102: Technician or assistant | H102: Yes | I102: Weeks 7 to 8 (Ink 2) | J102: No | L102: =IF(E102="","",IF(OR(AND(K102="Plan A",'All weeks'!$C$5="B"),AND(K102="Plan B",'All weeks'!$C$5="A")),0,IF(H102="Yes",E102,E102*IF(B102="Year 7",'All weeks'!$C$3,'All weeks'!$C$4)))) -> 10
...

Sheet Cut the prep
A1: Cutting the prep
A2: Where the prep time goes for one class, and the options for reducing it. Minutes link to the Prep by week sheet; the lessons themselves are unchanged.
A4: 1. Do all the printing in one request before Week 1
A5: Send the whole term's printing to reprographics at once (sheet totals below, from the All weeks sheet). Printing and sorting then stops being a weekly job.
C6: Printing tasks in the prep list (min, one class) | D6: =SUMIFS('Prep by week'!$E$19:$E$380,'Prep by week'!$G$19:$G$380,"Reprographics",'Prep by week'!$J$19:$J$380,"No") -> 196
C7: A4 paper (sheets, all weeks) | D7: =SUMIFS('All weeks'!$L$9:$L$721,'All weeks'!$J$9:$J$721,"A4 paper") -> 1987
C8: A3 paper (sheets, all weeks) | D8: =SUMIFS('All weeks'!$L$9:$L$721,'All weeks'!$J$9:$J$721,"A3 paper") -> 36
C9: A5 paper (sheets, all weeks) | D9: =SUMIFS('All weeks'!$L$9:$L$721,'All weeks'!$J$9:$J$721,"A5 paper") -> 160
C10: A4 card (sheets, all weeks) | D10: =SUMIFS('All weeks'!$L$9:$L$721,'All weeks'!$J$9:$J$721,"A4 card") -> 176
C11: A4 90 gsm (booklet) (sheets, all weeks) | D11: =SUMIFS('All weeks'!$L$9:$L$721,'All weeks'!$J$9:$J$721,"A4 90 gsm (booklet)") -> 196
A13: 2. Hand tasks to a technician, an assistant or the students
A14: Tasks marked as something someone else could do: buying, cutting, counting out kit, setting out trays, clean-up roles.
C15: Technician or assistant (min, one class) | D15: =SUMIFS('Prep by week'!$E$19:$E$380,'Prep by week'!$G$19:$G$380,"Technician or assistant",'Prep by week'!$J$19:$J$380,"No") -> 1306
C16: Students in the lesson (min, one class) | D16: =SUMIFS('Prep by week'!$E$19:$E$380,'Prep by week'!$G$19:$G$380,"Students (roles)",'Prep by week'!$J$19:$J$380,"No") -> 56
C17: Teacher only (min, one class) | D17: =SUMIFS('Prep by week'!$E$19:$E$380,'Prep by week'!$G$19:$G$380,"Teacher",'Prep by week'!$J$19:$J$380,"No") -> 2024
A19: 3. Make the reusable sets once, in one session before Week 1
A20: These are made once and reused in later weeks and by every class. Doing them together saves setting up and packing away each time.
A21: Week | B21: Year | C21: Task | D21: Minutes | E21: Reused
A22: 1 | B22: Year 7 | C22: Send the booklet jobs to reprographics: Scientist's Logbook (24 per class) and My Science Dictionary (28 per class, A5 saddle-stitched, 24 or 28 pages, 90 gsm). | D22: 10 | E22: Weeks 2 to 10
A23: 1 | B23: Year 7 | C23: Print the three A3 posters (Instruction words, Classroom language side B, Think in any language) and the A4 sentence frame poster; put them up on the wall. | D23: 15 | E23: Weeks 2 to 10
A24: 1 | B24: Year 8 | C24: Order the kit: 8 black washable felt-tip pens (four brands, two of each), coffee filters, masking tape, 24 A4 folders, 49 sheets of white A4 card, A3 paper, laminating pouches (6 A4, 30 A5), 24 pencils and a class box; plain bar soap and baking soda if using the scene table. | D24: 15 | E24: Pens: Week 3; folders and class box: Weeks 2 to 10
A25: 1 | B25: Year 8 | C25: Check the Skills Check master is final (native-speaker fixes made) before the print run, then freeze it unchanged until Week 10. | D25: 5 | E25: Week 10 (same master)
A26: 1 | B26: Year 8 | C26: Ask the school nurse or form tutors for the allergy list (needed for the Week 4 powders). | D26: 5 | E26: Weeks 4 and 5
A27: 1 | B27: Year 8 | C27: Run the pen pre-test (Case Bible Section 11): cut 4 coffee-filter strips 2 cm by 10 cm, pencil line 2 cm up, one dot per pen, stand in cups of water 1 cm deep for 6 to 8 minutes; check four clearly different patterns; choose pen B; cover brand names with masking tape and label A to D; record on the Teacher Pre-test Record; keep the dried strips. The Teacher Guide puts this in the Week 1 week; do it before the lesson if the pen-B note is wanted for the scene table or a slide photo. | D27: 20 | E27: Week 3 (pens, answer key)
A28: 1 | B28: Year 8 | C28: Write the display note with pen B on plain white card (exact text, snowflake doodle after 'Sorry!'); photograph it for Slide 5 if wanted. | D28: 5 | E28: Week 3 Hook
A29: 1 | B29: Year 8 | C29: Put up the three A3 language posters, the A4 frame poster and the A3 scene map; put a frame card set and a role card set on each group table. | D29: 10 | E29: All term
A30: 2 | B30: Year 7 | C30: Make 12 mystery cups: one object in each opaque cup, second cup upside down on top (rim to rim), tape all round with masking tape, label A to L underneath; keep the key on the teacher desk | D30: 15 | E30: Kept in the teacher box for future years
A31: 2 | B31: Year 8 | C31: Order the kit on the outline's Buy list (Teacher Guide prep calendar, before Week 1): soft pencils 2B to 4B (24), clear sticky tape (6 rolls), A4 white card (12 sheets per class for the record cards) | D31: 10 | E31: Tape rolls reused in Week 3
A32: 2 | B32: Year 8 | C32: Kit card teacher prep, printing (Teacher Guide prep calendar, Week 1 row): print the fingerprint record cards on A4 white card, 2 per sheet (A5 landscape, single-sided), and cut in half: 12 sheets = 24 cards per class; print the Fingerprint File, 7 A4 single-sided copies per class (6 groups + 1 display). Check the scene print is clearly a loop but smudged at the centre and no pattern names are on the sheet (Case Bible Section 12: 10 minutes) | D32: 10 | E32: Record cards stay in the case files
A33: 2 | B33: Year 8 | C33: After the last class: return the magnifying glasses, trays and cloths to the prep room; keep the 6 tape rolls for Week 3 | D33: 3 | E33: Tape rolls reused in Week 3
... A65: 10 | B65: Year 7 | C65: Write three lines for next year's teacher: what worked, what to change (for example the trial result and sample thickness) and anything to buy earlier | D65: 10 | E65: Next year's Ice Engineers series
A67: 4. Separate the marking and admin from the prep
A68: Much of the time in Weeks 1, 5 and 10 is marking the skills checks and checkpoints, entering the tracker and putting kit away after the lesson, not getting ready for it.
C69: After the lesson (min, one class) | D69: =SUMIFS('Prep by week'!$E$19:$E$380,'Prep by week'!$C$19:$C$380,"After the lesson",'Prep by week'!$J$19:$J$380,"No") -> 1630
C70: Before the lesson (min, one class) | D70: =SUMIFS('Prep by week'!$E$19:$E$380,'Prep by week'!$C$19:$C$380,"<>After the lesson",'Prep by week'!$J$19:$J$380,"No") -> 1952
A72: 5. Drop or simplify the optional extras
A73: Optional tasks are not counted in the totals; skipping them costs nothing in the lesson plan.
C74: Optional extras (min, one class) | D74: =SUMIFS('Prep by week'!$E$19:$E$380,'Prep by week'!$J$19:$J$380,"Optional") -> 280
A76: 6. The heaviest lessons (one class, before and after the lesson, both freezer plans counted)
A77: Week | B77: Year | C77: Lesson | D77: Minutes
A78: 10 | B78: Year 8 | C78: Court of Science | D78: 395
A79: 10 | B79: Year 7 | C79: Ice Engineers Expo | D79: 381
A80: 1 | B80: Year 8 | C80: Think like a detective | D80: 325
A81: 1 | B81: Year 7 | C81: What do scientists do? | D81: 295
A82: 8 | B82: Year 8 | C82: Lab day | D82: 283
A83: 7 | B83: Year 7 | C83: The ice ship mission | D83: 210
